{
  "linguisticTags": {
    "expression": "",
    "adverb": "",
    "noun": "",
    "pronoun": ""
  },
  "version": "17",
  "globalSpeed": "1.674286",
  "globalRepetitions": "1",
  "facialExpressions": [
    [
      "1",
      "Neutra"
    ],
    [
      "1.313131",
      "Neutra"
    ],
    [
      "1.616161",
      "Neutra"
    ],
    [
      "1.919192",
      "Neutra"
    ],
    [
      "2.212121",
      "Neutra"
    ],
    [
      "2.525252",
      "Neutra"
    ]
  ],
  "leftHandPoses": [
    [
      "1",
      "-"
    ],
    [
      "1.313131",
      "-"
    ],
    [
      "1.616161",
      "-"
    ],
    [
      "1.919192",
      "-"
    ],
    [
      "2.212121",
      "-"
    ],
    [
      "2.525252",
      "-"
    ]
  ],
  "rightHandPoses": [
    [
      "1",
      "indicativa eu"
    ],
    [
      "1.313131",
      "indicativa"
    ],
    [
      "1.616161",
      "indicativa eu"
    ],
    [
      "1.919192",
      "indicativa"
    ],
    [
      "2.212121",
      "indicativa eu"
    ],
    [
      "2.525252",
      "indicativa"
    ]
  ],
  "leftHandPositions": [
    {
      "time": "1",
      "x": "-0.2132077",
      "y": "0",
      "z": "0"
    },
    {
      "time": "1.313131",
      "x": "-0.2132077",
      "y": "0",
      "z": "0"
    },
    {
      "time": "1.616161",
      "x": "-0.2132077",
      "y": "0",
      "z": "0"
    },
    {
      "time": "1.919192",
      "x": "-0.2132077",
      "y": "0",
      "z": "0"
    },
    {
      "time": "2.212121",
      "x": "-0.2132077",
      "y": "0",
      "z": "0"
    },
    {
      "time": "2.525252",
      "x": "-0.2056561",
      "y": "0.004054077",
      "z": "-0.07523299"
    }
  ],
  "rightHandPositions": [
    {
      "time": "1",
      "x": "-0.2132077",
      "y": "0",
      "z": "0"
    },
    {
      "time": "1.313131",
      "x": "-0.2132077",
      "y": "0",
      "z": "0"
    },
    {
      "time": "1.616161",
      "x": "-0.2132077",
      "y": "0",
      "z": "0"
    },
    {
      "time": "1.919192",
      "x": "-0.2132077",
      "y": "0",
      "z": "0"
    },
    {
      "time": "2.212121",
      "x": "-0.2132077",
      "y": "0",
      "z": "0"
    },
    {
      "time": "2.525252",
      "x": "0.09414864",
      "y": "-0.205907",
      "z": "0.4931264"
    }
  ]
}
