{
  "linguisticTags": {
    "expression": "",
    "adverb": "",
    "noun": "",
    "pronoun": "",
    "verb": ""
  },
  "version": "17",
  "globalSpeed": "1.331429",
  "globalRepetitions": "2",
  "facialExpressions": [
    [
      "1",
      "Neutra"
    ],
    [
      "1.368687",
      "Neutra"
    ],
    [
      "1.717172",
      "Neutra"
    ],
    [
      "2.10101",
      "Neutra"
    ]
  ],
  "leftHandPoses": [
    [
      "1",
      "-"
    ],
    [
      "1.368687",
      "-"
    ],
    [
      "1.717172",
      "-"
    ],
    [
      "2.10101",
      "-"
    ]
  ],
  "rightHandPoses": [
    [
      "1",
      "4uBjw"
    ],
    [
      "1.368687",
      "4uBjw"
    ],
    [
      "1.717172",
      "4uBjw"
    ],
    [
      "2.10101",
      "4uBjw"
    ]
  ],
  "leftHandPositions": [
    {
      "time": "1",
      "x": "-0.2132077",
      "y": "0",
      "z": "0"
    },
    {
      "time": "1.368687",
      "x": "-0.2132077",
      "y": "0",
      "z": "0"
    },
    {
      "time": "1.717172",
      "x": "-0.2132077",
      "y": "0",
      "z": "0"
    },
    {
      "time": "2.10101",
      "x": "-0.2056561",
      "y": "0.003077514",
      "z": "-0.07498885"
    }
  ],
  "rightHandPositions": [
    {
      "time": "1",
      "x": "-0.2132077",
      "y": "0",
      "z": "0"
    },
    {
      "time": "1.368687",
      "x": "-0.2132077",
      "y": "0",
      "z": "0"
    },
    {
      "time": "1.717172",
      "x": "-0.2132077",
      "y": "0",
      "z": "0"
    },
    {
      "time": "2.10101",
      "x": "0.1380939",
      "y": "-0.1414538",
      "z": "0.3918081"
    }
  ]
}
