{
  "linguisticTags": {
    "expression": "",
    "adverb": "",
    "noun": "",
    "pronoun": "",
    "verb": ""
  },
  "version": "17",
  "globalSpeed": "1",
  "globalRepetitions": "1",
  "facialExpressions": [
    [
      "1",
      "Língua Fora"
    ],
    [
      "1.510101",
      "Língua Fora"
    ],
    [
      "2",
      "Língua Fora"
    ]
  ],
  "leftHandPoses": [
    [
      "1",
      "4OC-"
    ],
    [
      "1.510101",
      "4OC-"
    ],
    [
      "2",
      "4OC-"
    ]
  ],
  "rightHandPoses": [
    [
      "1",
      "4OC-"
    ],
    [
      "1.510101",
      "4OC-"
    ],
    [
      "2",
      "4OC-"
    ]
  ],
  "leftHandPositions": [
    {
      "time": "1",
      "x": "-0.2132077",
      "y": "0",
      "z": "0"
    },
    {
      "time": "1.510101",
      "x": "-0.2132077",
      "y": "0",
      "z": "0"
    },
    {
      "time": "2",
      "x": "-0.03280449",
      "y": "-0.1326647",
      "z": "0.251183"
    }
  ],
  "rightHandPositions": [
    {
      "time": "1",
      "x": "-0.2132077",
      "y": "0",
      "z": "0"
    },
    {
      "time": "1.510101",
      "x": "-0.2132077",
      "y": "0",
      "z": "0"
    },
    {
      "time": "2",
      "x": "0.08047676",
      "y": "-0.2068835",
      "z": "0.313683"
    }
  ]
}
