{
  "linguisticTags": {
    "expression": "",
    "adverb": "",
    "noun": "",
    "pronoun": "",
    "verb": ""
  },
  "version": "17",
  "globalSpeed": "1",
  "globalRepetitions": "1",
  "facialExpressions": [
    [
      "1.055555",
      "Neutra"
    ],
    [
      "1.843434",
      "Neutra"
    ]
  ],
  "leftHandPoses": [
    [
      "1.055555",
      "1OR\u002Be"
    ],
    [
      "1.843434",
      "1OR-e"
    ]
  ],
  "rightHandPoses": [
    [
      "1.055555",
      "1OR\u002Be"
    ],
    [
      "1.843434",
      "1OR-e"
    ]
  ],
  "leftHandPositions": [
    {
      "time": "1.055555",
      "x": "-0.2132077",
      "y": "0",
      "z": "0"
    },
    {
      "time": "1.843434",
      "x": "-0.06405449",
      "y": "-0.2283679",
      "z": "0.2755971"
    }
  ],
  "rightHandPositions": [
    {
      "time": "1.055555",
      "x": "-0.2132077",
      "y": "0",
      "z": "0"
    },
    {
      "time": "1.843434",
      "x": "0.05313301",
      "y": "-0.2205554",
      "z": "0.2912221"
    }
  ]
}
