{
  "linguisticTags": {},
  "version": "17",
  "globalSpeed": "1",
  "globalRepetitions": "1",
  "facialExpressions": [
    [
      "0",
      "Neutra"
    ]
  ],
  "leftHandPoses": [
    [
      "1",
      "-"
    ]
  ],
  "rightHandPoses": [
    [
      "1",
      "P"
    ]
  ],
  "leftHandPositions": [
    {
      "time": "1",
      "x": "-0.2052898",
      "y": "0.003321655",
      "z": "-0.07529403"
    }
  ],
  "rightHandPositions": [
    {
      "time": "1",
      "x": "0.04776192",
      "y": "-0.1617175",
      "z": "0.2386708"
    }
  ]
}
