{
  "animTracks": [
    {
      "properties": [
        "Right Hand Configuration",
        "Left Hand Configuration",
        "Muscles",
        "Facial Expression"
      ],
      "loops": false,
      "keyFrames": [
        {
          "property": "Muscles",
          "index": 3,
          "time": 3.01010084,
          "ints": {},
          "floats": {
            "muscle0": 2.15925563E-12,
            "muscle1": 2.68220703E-07,
            "muscle2": -2.03555451E-14,
            "muscle3": -1.48849899E-12,
            "muscle4": -1.69222731E-25,
            "muscle5": -3.25688776E-13,
            "muscle6": 0,
            "muscle7": 0,
            "muscle8": 0,
            "muscle9": -3.96933029E-13,
            "muscle10": -4.0711097E-14,
            "muscle11": -3.25688776E-13,
            "muscle12": 3.84197818E-07,
            "muscle13": -1.67114447E-08,
            "muscle14": -2.49923801E-07,
            "muscle15": 0,
            "muscle16": 9.75310357E-08,
            "muscle17": 0,
            "muscle18": -2.60550999E-12,
            "muscle19": 0,
            "muscle20": 0,
            "muscle21": 0.518864214,
            "muscle22": -0.0599374473,
            "muscle23": -0.145370975,
            "muscle24": 0.917206466,
            "muscle25": 0.129595056,
            "muscle26": -0.0660294294,
            "muscle27": 0.0832163543,
            "muscle28": 2.37989369E-07,
            "muscle29": 0.518861949,
            "muscle30": -0.0599405207,
            "muscle31": -0.145377323,
            "muscle32": 0.917205215,
            "muscle33": 0.129600197,
            "muscle34": -0.0659822747,
            "muscle35": 0.0832239166,
            "muscle36": 3.996727E-07,
            "muscle37": -0.499998987,
            "muscle38": 0.00360269262,
            "muscle39": -0.518130541,
            "muscle40": 0.211261004,
            "muscle41": -0.026458459,
            "muscle42": 0.982118368,
            "muscle43": 0.125619501,
            "muscle44": -0.0197714921,
            "muscle45": 0.022564074,
            "muscle46": -0.499996513,
            "muscle47": 0.00360632734,
            "muscle48": -0.518350661,
            "muscle49": 0.0221998692,
            "muscle50": 0.109430254,
            "muscle51": -0.411240667,
            "muscle52": 0.558448732,
            "muscle53": -0.689881504,
            "muscle54": -0.87084204,
            "muscle55": -1.36603751E-06,
            "muscle56": 6.83018584E-08,
            "muscle57": 3.64950097E-08,
            "muscle58": 9.11422333E-08,
            "muscle59": -6.83018726E-08,
            "muscle60": 8.53773443E-08,
            "muscle61": -7.58909735E-08,
            "muscle62": -2.20871803E-18,
            "muscle63": 6.83018939E-08,
            "muscle64": -2.2767297E-07,
            "muscle65": -7.58909806E-08,
            "muscle66": 4.96961642E-17,
            "muscle67": 3.41509399E-08,
            "muscle68": -1.13836471E-07,
            "muscle69": -6.07127788E-07,
            "muscle70": -2.76089676E-19,
            "muscle71": -3.41509399E-08,
            "muscle72": 4.26886793E-08,
            "muscle73": 1.51781947E-07,
            "muscle74": 0,
            "muscle75": -1.80000031,
            "muscle76": 0.105554894,
            "muscle77": -0.271117955,
            "muscle78": 0.799999356,
            "muscle79": 0.0888886005,
            "muscle80": -1.0180279,
            "muscle81": -1.33333349,
            "muscle82": -0.360000551,
            "muscle83": -0.999999523,
            "muscle84": -0.436818093,
            "muscle85": -2.00000095,
            "muscle86": 0.999999464,
            "muscle87": -0.99999994,
            "muscle88": 0.271548301,
            "muscle89": -2.00000095,
            "muscle90": 0.999999404,
            "muscle91": -0.99999994,
            "muscle92": 0.695616364,
            "muscle93": -2.00000072,
            "muscle94": 0.999999464,
            "duration": 0,
            "muscle-1": 1
          },
          "strings": {
            "interpolation": "smooth"
          },
          "inTangent": 0,
          "inWeight": 0,
          "outTangent": 0,
          "outWeight": 0,
          "weightedMode": 0
        },
        {
          "property": "Muscles",
          "index": 2,
          "time": 2.5151515,
          "ints": {},
          "floats": {
            "muscle0": 2.15925563E-12,
            "muscle1": 2.68220703E-07,
            "muscle2": -2.03555451E-14,
            "muscle3": -1.48849899E-12,
            "muscle4": -1.69222731E-25,
            "muscle5": -3.25688776E-13,
            "muscle6": 0,
            "muscle7": 0,
            "muscle8": 0,
            "muscle9": -3.96933029E-13,
            "muscle10": -4.0711097E-14,
            "muscle11": -3.25688776E-13,
            "muscle12": 3.62853484E-07,
            "muscle13": 2.83103785E-09,
            "muscle14": 9.36874827E-08,
            "muscle15": 0,
            "muscle16": -3.13225756E-09,
            "muscle17": 0,
            "muscle18": -2.60550999E-12,
            "muscle19": 0,
            "muscle20": 0,
            "muscle21": 0.519552112,
            "muscle22": -0.0619128458,
            "muscle23": -0.184096813,
            "muscle24": 0.920473695,
            "muscle25": 0.155513465,
            "muscle26": -0.0655886084,
            "muscle27": 0.0796553642,
            "muscle28": 2.37989369E-07,
            "muscle29": 0.519549727,
            "muscle30": -0.0619183294,
            "muscle31": -0.184104517,
            "muscle32": 0.920472801,
            "muscle33": 0.155520111,
            "muscle34": -0.0655408725,
            "muscle35": 0.0796662048,
            "muscle36": 1.94633657E-07,
            "muscle37": -0.499998987,
            "muscle38": 0.00360269262,
            "muscle39": -0.517632246,
            "muscle40": 0.211223975,
            "muscle41": -0.0377018116,
            "muscle42": 0.982964158,
            "muscle43": 0.136789858,
            "muscle44": -0.0194140691,
            "muscle45": 0.0224185549,
            "muscle46": -0.499997675,
            "muscle47": 0.00360540743,
            "muscle48": -0.518520236,
            "muscle49": 0.0222026221,
            "muscle50": 0.109507389,
            "muscle51": -0.411259443,
            "muscle52": -1.19976509,
            "muscle53": -0.183154345,
            "muscle54": -0.384503156,
            "muscle55": -1.70754674E-07,
            "muscle56": -6.83018811E-07,
            "muscle57": 3.64950097E-08,
            "muscle58": 9.11422333E-08,
            "muscle59": -5.12264137E-07,
            "muscle60": 2.56132068E-07,
            "muscle61": -7.58909735E-08,
            "muscle62": -2.20871803E-18,
            "muscle63": -3.75660363E-07,
            "muscle64": -4.66481246E-15,
            "muscle65": -7.58909806E-08,
            "muscle66": 4.96961642E-17,
            "muscle67": 2.3905659E-07,
            "muscle68": -2.96851675E-15,
            "muscle69": -1.51781947E-07,
            "muscle70": -2.76089676E-19,
            "muscle71": -3.41509399E-08,
            "muscle72": 4.26886793E-08,
            "muscle73": 1.51781947E-07,
            "muscle74": 0,
            "muscle75": -1.80000031,
            "muscle76": 0.105554976,
            "muscle77": -0.271117955,
            "muscle78": 0.799999356,
            "muscle79": 0.0888886005,
            "muscle80": -1.0180279,
            "muscle81": -1.33333349,
            "muscle82": -0.360000551,
            "muscle83": -0.999999523,
            "muscle84": -0.436818093,
            "muscle85": -2.00000095,
            "muscle86": 0.999999702,
            "muscle87": -0.99999994,
            "muscle88": 0.271548301,
            "muscle89": -2.00000095,
            "muscle90": 0.999999404,
            "muscle91": -1,
            "muscle92": 0.695616066,
            "muscle93": -2.00000072,
            "muscle94": 0.999999702,
            "duration": 0,
            "muscle-1": 1
          },
          "strings": {
            "interpolation": "smooth"
          },
          "inTangent": 0,
          "inWeight": 0,
          "outTangent": 0,
          "outWeight": 0,
          "weightedMode": 0
        },
        {
          "property": "Muscles",
          "index": 1,
          "time": 1.99999988,
          "ints": {},
          "floats": {
            "muscle0": 2.15925563E-12,
            "muscle1": 2.68220703E-07,
            "muscle2": -2.03555451E-14,
            "muscle3": -1.48849899E-12,
            "muscle4": -1.69222731E-25,
            "muscle5": -3.25688776E-13,
            "muscle6": 0,
            "muscle7": 0,
            "muscle8": 0,
            "muscle9": -3.96933029E-13,
            "muscle10": -4.0711097E-14,
            "muscle11": -3.25688776E-13,
            "muscle12": 3.62853484E-07,
            "muscle13": 2.83103785E-09,
            "muscle14": 9.36874827E-08,
            "muscle15": 0,
            "muscle16": -3.13225756E-09,
            "muscle17": 0,
            "muscle18": -2.60550999E-12,
            "muscle19": 0,
            "muscle20": 0,
            "muscle21": 0.519552112,
            "muscle22": -0.0619128458,
            "muscle23": -0.184096813,
            "muscle24": 0.920473695,
            "muscle25": 0.155513465,
            "muscle26": -0.0655886084,
            "muscle27": 0.0796553642,
            "muscle28": 2.37989369E-07,
            "muscle29": 0.519549668,
            "muscle30": -0.0619183294,
            "muscle31": -0.184103563,
            "muscle32": 0.920472682,
            "muscle33": 0.155519798,
            "muscle34": -0.065541029,
            "muscle35": 0.0796669275,
            "muscle36": 1.94633657E-07,
            "muscle37": -0.499998987,
            "muscle38": 0.00360269262,
            "muscle39": -0.517632246,
            "muscle40": 0.211223975,
            "muscle41": -0.0377018116,
            "muscle42": 0.982964158,
            "muscle43": 0.136789858,
            "muscle44": -0.0194140691,
            "muscle45": 0.0224185549,
            "muscle46": -0.499997675,
            "muscle47": 0.00360540743,
            "muscle48": -0.518522024,
            "muscle49": 0.0222003944,
            "muscle50": 0.109506533,
            "muscle51": -0.411259711,
            "muscle52": 0.558445394,
            "muscle53": -0.689969659,
            "muscle54": -0.870594203,
            "muscle55": -1.70754674E-07,
            "muscle56": -6.83018811E-07,
            "muscle57": 3.64950097E-08,
            "muscle58": 9.11422333E-08,
            "muscle59": -5.12264137E-07,
            "muscle60": 2.56132068E-07,
            "muscle61": -7.58909735E-08,
            "muscle62": -2.20871803E-18,
            "muscle63": -3.75660363E-07,
            "muscle64": -4.66481246E-15,
            "muscle65": -7.58909806E-08,
            "muscle66": 4.96961642E-17,
            "muscle67": 2.3905659E-07,
            "muscle68": -2.96851675E-15,
            "muscle69": -1.51781947E-07,
            "muscle70": -2.76089676E-19,
            "muscle71": -3.41509399E-08,
            "muscle72": 4.26886793E-08,
            "muscle73": 1.51781947E-07,
            "muscle74": 0,
            "muscle75": -1.80000031,
            "muscle76": 0.105554976,
            "muscle77": -0.271117955,
            "muscle78": 0.799999356,
            "muscle79": 0.0888886005,
            "muscle80": -1.0180279,
            "muscle81": -1.33333349,
            "muscle82": -0.360000551,
            "muscle83": -0.999999523,
            "muscle84": -0.436818093,
            "muscle85": -2.00000095,
            "muscle86": 0.999999464,
            "muscle87": -0.99999994,
            "muscle88": 0.271546811,
            "muscle89": -2.00000095,
            "muscle90": 0.999999404,
            "muscle91": -1,
            "muscle92": 0.695616066,
            "muscle93": -2.00000072,
            "muscle94": 0.999999464,
            "duration": 0,
            "muscle-1": 1
          },
          "strings": {
            "interpolation": "smooth"
          },
          "inTangent": 0,
          "inWeight": 0,
          "outTangent": 0,
          "outWeight": 0,
          "weightedMode": 0
        },
        {
          "property": "Muscles",
          "index": 4,
          "time": 0.999999881,
          "ints": {},
          "floats": {
            "muscle0": 2.15925563E-12,
            "muscle1": 2.68220703E-07,
            "muscle2": -2.03555451E-14,
            "muscle3": -1.48849899E-12,
            "muscle4": -1.69222731E-25,
            "muscle5": -3.25688776E-13,
            "muscle6": 0,
            "muscle7": 0,
            "muscle8": 0,
            "muscle9": -3.96933029E-13,
            "muscle10": -4.0711097E-14,
            "muscle11": -3.25688776E-13,
            "muscle12": 3.84197818E-07,
            "muscle13": 2.01176533E-08,
            "muscle14": -1.618602E-07,
            "muscle15": 0,
            "muscle16": 4.83886538E-07,
            "muscle17": 0,
            "muscle18": -2.60550999E-12,
            "muscle19": 0,
            "muscle20": 0,
            "muscle21": 0.520540476,
            "muscle22": -0.06438642,
            "muscle23": -0.236123174,
            "muscle24": 0.924839258,
            "muscle25": 0.190326795,
            "muscle26": -0.0649158061,
            "muscle27": 0.0751779452,
            "muscle28": 3.74593156E-07,
            "muscle29": 0.520538032,
            "muscle30": -0.0643930584,
            "muscle31": -0.236131251,
            "muscle32": 0.924838722,
            "muscle33": 0.190334186,
            "muscle34": -0.0648680627,
            "muscle35": 0.0751916021,
            "muscle36": 9.46487944E-07,
            "muscle37": -0.499998987,
            "muscle38": 0.00360289821,
            "muscle39": -0.516929448,
            "muscle40": 0.211163282,
            "muscle41": -0.054008577,
            "muscle42": 0.984187543,
            "muscle43": 0.152994528,
            "muscle44": -0.0189104192,
            "muscle45": 0.0221959297,
            "muscle46": -0.499998987,
            "muscle47": 0.00360562769,
            "muscle48": -0.518692434,
            "muscle49": 0.022201702,
            "muscle50": 0.109583065,
            "muscle51": -0.411278605,
            "muscle52": 0.558442712,
            "muscle53": -0.690058291,
            "muscle54": -0.870347738,
            "muscle55": -1.017777E-14,
            "muscle56": 1.36603745E-07,
            "muscle57": 3.64950097E-08,
            "muscle58": 9.11422333E-08,
            "muscle59": -5.12264137E-07,
            "muscle60": 2.56132068E-07,
            "muscle61": -7.58909735E-08,
            "muscle62": -2.20871803E-18,
            "muscle63": 6.83018939E-08,
            "muscle64": -2.2767297E-07,
            "muscle65": -4.55345855E-07,
            "muscle66": 4.96961642E-17,
            "muscle67": 2.3905659E-07,
            "muscle68": -2.96851675E-15,
            "muscle69": -6.07127788E-07,
            "muscle70": -2.76089676E-19,
            "muscle71": -3.41509399E-08,
            "muscle72": 4.26886793E-08,
            "muscle73": 1.51781947E-07,
            "muscle74": 0,
            "muscle75": -1.80000031,
            "muscle76": 0.105554976,
            "muscle77": -0.271117955,
            "muscle78": 0.799999356,
            "muscle79": 0.0888886005,
            "muscle80": -1.0180279,
            "muscle81": -1.33333349,
            "muscle82": -0.360000551,
            "muscle83": -0.999999523,
            "muscle84": -0.436818093,
            "muscle85": -2.00000095,
            "muscle86": 0.999999702,
            "muscle87": -0.99999994,
            "muscle88": 0.271548301,
            "muscle89": -2.00000095,
            "muscle90": 0.999999404,
            "muscle91": -1,
            "muscle92": 0.695616066,
            "muscle93": -2.00000072,
            "muscle94": 0.999999702,
            "duration": 0,
            "muscle-1": 1
          },
          "strings": {
            "interpolation": "smooth"
          },
          "inTangent": 0,
          "inWeight": 0,
          "outTangent": 0,
          "outWeight": 0,
          "weightedMode": 0
        },
        {
          "property": "Muscles",
          "index": 5,
          "time": 1.51515174,
          "ints": {},
          "floats": {
            "muscle0": 2.15925563E-12,
            "muscle1": 2.68220703E-07,
            "muscle2": -2.03555451E-14,
            "muscle3": -1.48849899E-12,
            "muscle4": -1.69222731E-25,
            "muscle5": -3.25688776E-13,
            "muscle6": 0,
            "muscle7": 0,
            "muscle8": 0,
            "muscle9": -3.96933029E-13,
            "muscle10": -4.0711097E-14,
            "muscle11": -3.25688776E-13,
            "muscle12": 3.84197818E-07,
            "muscle13": 2.01176533E-08,
            "muscle14": -1.618602E-07,
            "muscle15": 0,
            "muscle16": 4.83886538E-07,
            "muscle17": 0,
            "muscle18": -2.60550999E-12,
            "muscle19": 0,
            "muscle20": 0,
            "muscle21": 0.520540476,
            "muscle22": -0.06438642,
            "muscle23": -0.236123174,
            "muscle24": 0.924839258,
            "muscle25": 0.190326795,
            "muscle26": -0.0649158061,
            "muscle27": 0.0751779452,
            "muscle28": 3.74593156E-07,
            "muscle29": 0.520538032,
            "muscle30": -0.0643930584,
            "muscle31": -0.236131251,
            "muscle32": 0.924838722,
            "muscle33": 0.190334186,
            "muscle34": -0.0648680627,
            "muscle35": 0.0751916021,
            "muscle36": 9.46487944E-07,
            "muscle37": -0.499998987,
            "muscle38": 0.00360289821,
            "muscle39": -0.516929448,
            "muscle40": 0.211163282,
            "muscle41": -0.054008577,
            "muscle42": 0.984187543,
            "muscle43": 0.152994528,
            "muscle44": -0.0189104192,
            "muscle45": 0.0221959297,
            "muscle46": -0.499998987,
            "muscle47": 0.00360562769,
            "muscle48": -0.518692434,
            "muscle49": 0.022201702,
            "muscle50": 0.109583065,
            "muscle51": -0.411278605,
            "muscle52": -1.19985712,
            "muscle53": -0.183116287,
            "muscle54": -0.384752333,
            "muscle55": -1.017777E-14,
            "muscle56": 1.36603745E-07,
            "muscle57": 3.64950097E-08,
            "muscle58": 9.11422333E-08,
            "muscle59": -5.12264137E-07,
            "muscle60": 2.56132068E-07,
            "muscle61": -7.58909735E-08,
            "muscle62": -2.20871803E-18,
            "muscle63": 6.83018939E-08,
            "muscle64": -2.2767297E-07,
            "muscle65": -4.55345855E-07,
            "muscle66": 4.96961642E-17,
            "muscle67": 2.3905659E-07,
            "muscle68": -2.96851675E-15,
            "muscle69": -6.07127788E-07,
            "muscle70": -2.76089676E-19,
            "muscle71": -3.41509399E-08,
            "muscle72": 4.26886793E-08,
            "muscle73": 1.51781947E-07,
            "muscle74": 0,
            "muscle75": -1.80000031,
            "muscle76": 0.105554976,
            "muscle77": -0.271117955,
            "muscle78": 0.799999356,
            "muscle79": 0.0888886005,
            "muscle80": -1.0180279,
            "muscle81": -1.33333349,
            "muscle82": -0.360000551,
            "muscle83": -0.999999523,
            "muscle84": -0.436818093,
            "muscle85": -2.00000095,
            "muscle86": 0.999999702,
            "muscle87": -0.99999994,
            "muscle88": 0.271548301,
            "muscle89": -2.00000095,
            "muscle90": 0.999999404,
            "muscle91": -1,
            "muscle92": 0.695616066,
            "muscle93": -2.00000072,
            "muscle94": 0.999999702,
            "duration": 0,
            "muscle-1": 1
          },
          "strings": {
            "interpolation": "smooth"
          },
          "inTangent": 0,
          "inWeight": 0,
          "outTangent": 0,
          "outWeight": 0,
          "weightedMode": 0
        },
        {
          "property": "Left Hand Configuration",
          "index": 3,
          "time": 3.01010084,
          "ints": {
            "hash": -77835264
          },
          "floats": {
            "duration": 0
          },
          "strings": {
            "name": "-"
          },
          "inTangent": 0,
          "inWeight": 0,
          "outTangent": 0,
          "outWeight": 0,
          "weightedMode": 0
        },
        {
          "property": "Left Hand Configuration",
          "index": 2,
          "time": 2.5151515,
          "ints": {
            "hash": -1280823296
          },
          "floats": {
            "duration": 0
          },
          "strings": {
            "name": "-"
          },
          "inTangent": 0,
          "inWeight": 0,
          "outTangent": 0,
          "outWeight": 0,
          "weightedMode": 0
        },
        {
          "property": "Left Hand Configuration",
          "index": 1,
          "time": 1.99999988,
          "ints": {
            "hash": 444162048
          },
          "floats": {
            "duration": 0
          },
          "strings": {
            "name": "-"
          },
          "inTangent": 0,
          "inWeight": 0,
          "outTangent": 0,
          "outWeight": 0,
          "weightedMode": 0
        },
        {
          "property": "Left Hand Configuration",
          "index": 4,
          "time": 0.999999881,
          "ints": {
            "hash": 618554368
          },
          "floats": {
            "duration": 0
          },
          "strings": {
            "name": "-"
          },
          "inTangent": 0,
          "inWeight": 0,
          "outTangent": 0,
          "outWeight": 0,
          "weightedMode": 0
        },
        {
          "property": "Left Hand Configuration",
          "index": 5,
          "time": 1.51515174,
          "ints": {
            "hash": 734575616
          },
          "floats": {
            "duration": 0
          },
          "strings": {
            "name": "-"
          },
          "inTangent": 0,
          "inWeight": 0,
          "outTangent": 0,
          "outWeight": 0,
          "weightedMode": 0
        },
        {
          "property": "Right Hand Configuration",
          "index": 3,
          "time": 3.01010084,
          "ints": {
            "hash": -649914368
          },
          "floats": {
            "duration": 0
          },
          "strings": {
            "name": "1Hj"
          },
          "inTangent": 0,
          "inWeight": 0,
          "outTangent": 0,
          "outWeight": 0,
          "weightedMode": 0
        },
        {
          "property": "Right Hand Configuration",
          "index": 2,
          "time": 2.5151515,
          "ints": {
            "hash": 1869985792
          },
          "floats": {
            "duration": 0
          },
          "strings": {
            "name": "1Hj"
          },
          "inTangent": 0,
          "inWeight": 0,
          "outTangent": 0,
          "outWeight": 0,
          "weightedMode": 0
        },
        {
          "property": "Right Hand Configuration",
          "index": 1,
          "time": 1.99999988,
          "ints": {
            "hash": -127917056
          },
          "floats": {
            "duration": 0
          },
          "strings": {
            "name": "1Hj"
          },
          "inTangent": 0,
          "inWeight": 0,
          "outTangent": 0,
          "outWeight": 0,
          "weightedMode": 0
        },
        {
          "property": "Right Hand Configuration",
          "index": 4,
          "time": 0.999999881,
          "ints": {
            "hash": 2094858240
          },
          "floats": {
            "duration": 0
          },
          "strings": {
            "name": "1Hj"
          },
          "inTangent": 0,
          "inWeight": 0,
          "outTangent": 0,
          "outWeight": 0,
          "weightedMode": 0
        },
        {
          "property": "Right Hand Configuration",
          "index": 5,
          "time": 1.51515174,
          "ints": {
            "hash": -816017408
          },
          "floats": {
            "duration": 0
          },
          "strings": {
            "name": "1Hj"
          },
          "inTangent": 0,
          "inWeight": 0,
          "outTangent": 0,
          "outWeight": 0,
          "weightedMode": 0
        },
        {
          "property": "Facial Expression",
          "index": 3,
          "time": 3.01010084,
          "ints": {},
          "floats": {
            "duration": 0
          },
          "strings": {
            "faceName": "Neutra"
          },
          "inTangent": 0,
          "inWeight": 0,
          "outTangent": 0,
          "outWeight": 0,
          "weightedMode": 0
        },
        {
          "property": "Facial Expression",
          "index": 2,
          "time": 2.5151515,
          "ints": {},
          "floats": {
            "duration": 0
          },
          "strings": {
            "faceName": "Neutra"
          },
          "inTangent": 0,
          "inWeight": 0,
          "outTangent": 0,
          "outWeight": 0,
          "weightedMode": 0
        },
        {
          "property": "Facial Expression",
          "index": 1,
          "time": 1.99999988,
          "ints": {},
          "floats": {
            "duration": 0
          },
          "strings": {
            "faceName": "Neutra"
          },
          "inTangent": 0,
          "inWeight": 0,
          "outTangent": 0,
          "outWeight": 0,
          "weightedMode": 0
        },
        {
          "property": "Facial Expression",
          "index": 4,
          "time": 0.999999881,
          "ints": {},
          "floats": {
            "duration": 0
          },
          "strings": {
            "faceName": "Neutra"
          },
          "inTangent": 0,
          "inWeight": 0,
          "outTangent": 0,
          "outWeight": 0,
          "weightedMode": 0
        },
        {
          "property": "Facial Expression",
          "index": 5,
          "time": 1.51515174,
          "ints": {},
          "floats": {
            "duration": 0
          },
          "strings": {
            "faceName": "Neutra"
          },
          "inTangent": 0,
          "inWeight": 0,
          "outTangent": 0,
          "outWeight": 0,
          "weightedMode": 0
        }
      ]
    },
    {
      "properties": [
        "Face Animation Neutra"
      ],
      "loops": false,
      "keyFrames": [
        {
          "property": "Face Animation Neutra",
          "index": 0,
          "time": 0,
          "ints": {},
          "floats": {
            "girl_head_.blendShape.mClose": 100,
            "girl_head_.blendShape.A": 0,
            "girl_head_.blendShape.Cons": 0,
            "girl_head_.blendShape.Fv": 0,
            "girl_head_.blendShape.mLSide": 0,
            "girl_head_.blendShape.mLSideUp": 0,
            "girl_head_.blendShape.mRSide": 0,
            "girl_head_.blendShape.mRSideUp": 0,
            "girl_head_.blendShape.O": 0,
            "girl_head_.blendShape.smile": 0,
            "girl_head_.blendShape.U": 0,
            "girl_hair.blendShape.cheek1": 0,
            "girl_hair.blendShape.cheek2": 0,
            "girl_hair.blendShape.cheek3": 0,
            "girl_head_.blendShape.Bmp": 0,
            "girl_head_.blendShape.E": 0,
            "girl_head_.blendShape.F001": 0,
            "girl_head_.blendShape.F003": 0,
            "girl_head_.blendShape.F005": 0,
            "girl_head_.blendShape.F006": 0,
            "girl_head_.blendShape.F007": 0,
            "girl_head_.blendShape.F007left": 0,
            "girl_head_.blendShape.F008": 0,
            "girl_head_.blendShape.F017": 0,
            "girl_head_.blendShape.F019": 0,
            "girl_head_.blendShape.F024": 0,
            "girl_head_.blendShape.F031": 0,
            "girl_head_.blendShape.LEyeBMad": 0,
            "girl_head_.blendShape.LEyeClose": 0,
            "girl_head_.blendShape.LEyeLidUp": 0,
            "girl_head_.blendShape.LEyeMad": 0,
            "girl_head_.blendShape.LEyeSad": 0,
            "girl_head_.blendShape.LeyeBUp": 0,
            "girl_head_.blendShape.mSad": 0,
            "girl_head_.blendShape.REyeBMad": 0,
            "girl_head_.blendShape.REyeClose": 0,
            "girl_head_.blendShape.REyeLidUp": 0,
            "girl_head_.blendShape.REyeMad": 0,
            "girl_head_.blendShape.REyeSad": 0,
            "girl_head_.blendShape.ReyeBSad": 0,
            "girl_head_.blendShape.ReyeBUp": 0,
            "girl_head_.blendShape.ReyeLSad": 0,
            "tgrl1_dmyHeadObjsRoot/tgrl1_logGumTeethAngle/tgrl1_logGumTeethMove/tgrl1_tongue.blendShape.tongue_A": 0,
            "tgrl1_dmyHeadObjsRoot/tgrl1_logGumTeethAngle/tgrl1_logGumTeethMove/tgrl1_tongue.blendShape.tongue_down": 0,
            "tgrl1_dmyHeadObjsRoot/tgrl1_logGumTeethAngle/tgrl1_logGumTeethMove/tgrl1_tongue.blendShape.tongue_F007": 0,
            "tgrl1_dmyHeadObjsRoot/tgrl1_logGumTeethAngle/tgrl1_logGumTeethMove/tgrl1_tongue.blendShape.tongue_F007left": 0,
            "tgrl1_dmyHeadObjsRoot/tgrl1_logGumTeethAngle/tgrl1_logGumTeethMove/tgrl1_tongue.blendShape.tongue_left": 0,
            "tgrl1_dmyHeadObjsRoot/tgrl1_logGumTeethAngle/tgrl1_logGumTeethMove/tgrl1_tongue.blendShape.tongue_O": 0,
            "tgrl1_dmyHeadObjsRoot/tgrl1_logGumTeethAngle/tgrl1_logGumTeethMove/tgrl1_tongue.blendShape.tongue_out": 0,
            "tgrl1_dmyHeadObjsRoot/tgrl1_logGumTeethAngle/tgrl1_logGumTeethMove/tgrl1_tongue.blendShape.tongue_right": 0,
            "tgrl1_dmyHeadObjsRoot/tgrl1_logGumTeethAngle/tgrl1_logGumTeethMove/tgrl1_tongue.blendShape.tongue_up": 0,
            "rig_CharRoot/bip/bip Pelvis/bip Spine/bip Spine1/bip Neck/bip Head/rig_boneTongue.m_LocalPosition.x": -0.0188717656,
            "rig_CharRoot/bip/bip Pelvis/bip Spine/bip Spine1/bip Neck/bip Head/rig_boneTongue.m_LocalPosition.y": 0.0733392909,
            "rig_CharRoot/bip/bip Pelvis/bip Spine/bip Spine1/bip Neck/bip Head/rig_boneTongue.m_LocalPosition.z": 1.52587887E-07,
            "rig_CharRoot/bip/bip Pelvis/bip Spine/bip Spine1/bip Neck/bip Head/rig_boneTongue.localEulerAnglesRaw.x": 178.884003,
            "rig_CharRoot/bip/bip Pelvis/bip Spine/bip Spine1/bip Neck/bip Head/rig_boneTongue.localEulerAnglesRaw.y": 89.9999924,
            "rig_CharRoot/bip/bip Pelvis/bip Spine/bip Spine1/bip Neck/bip Head/rig_boneTongue.localEulerAnglesRaw.z": 0,
            "rig_CharRoot/bip/bip Pelvis/bip Spine/bip Spine1/bip Neck/bip Head/rig_boneTongue.m_LocalScale.x": 1,
            "rig_CharRoot/bip/bip Pelvis/bip Spine/bip Spine1/bip Neck/bip Head/rig_boneTongue.m_LocalScale.y": 1,
            "rig_CharRoot/bip/bip Pelvis/bip Spine/bip Spine1/bip Neck/bip Head/rig_boneTongue.m_LocalScale.z": 1,
            "muscle15": 0,
            "muscle17": 0
          },
          "strings": {},
          "inTangent": 0,
          "inWeight": 0.333333343,
          "outTangent": 0,
          "outWeight": 0.333333343,
          "weightedMode": 0
        }
      ]
    },
    {
      "properties": [
        "Face Animation Neutra"
      ],
      "loops": false,
      "keyFrames": [
        {
          "property": "Face Animation Neutra",
          "index": 0,
          "time": 0,
          "ints": {},
          "floats": {
            "girl_head_.blendShape.mClose": 100,
            "girl_head_.blendShape.A": 0,
            "girl_head_.blendShape.Cons": 0,
            "girl_head_.blendShape.Fv": 0,
            "girl_head_.blendShape.mLSide": 0,
            "girl_head_.blendShape.mLSideUp": 0,
            "girl_head_.blendShape.mRSide": 0,
            "girl_head_.blendShape.mRSideUp": 0,
            "girl_head_.blendShape.O": 0,
            "girl_head_.blendShape.smile": 0,
            "girl_head_.blendShape.U": 0,
            "girl_hair.blendShape.cheek1": 0,
            "girl_hair.blendShape.cheek2": 0,
            "girl_hair.blendShape.cheek3": 0,
            "girl_head_.blendShape.Bmp": 0,
            "girl_head_.blendShape.E": 0,
            "girl_head_.blendShape.F001": 0,
            "girl_head_.blendShape.F003": 0,
            "girl_head_.blendShape.F005": 0,
            "girl_head_.blendShape.F006": 0,
            "girl_head_.blendShape.F007": 0,
            "girl_head_.blendShape.F007left": 0,
            "girl_head_.blendShape.F008": 0,
            "girl_head_.blendShape.F017": 0,
            "girl_head_.blendShape.F019": 0,
            "girl_head_.blendShape.F024": 0,
            "girl_head_.blendShape.F031": 0,
            "girl_head_.blendShape.LEyeBMad": 0,
            "girl_head_.blendShape.LEyeClose": 0,
            "girl_head_.blendShape.LEyeLidUp": 0,
            "girl_head_.blendShape.LEyeMad": 0,
            "girl_head_.blendShape.LEyeSad": 0,
            "girl_head_.blendShape.LeyeBUp": 0,
            "girl_head_.blendShape.mSad": 0,
            "girl_head_.blendShape.REyeBMad": 0,
            "girl_head_.blendShape.REyeClose": 0,
            "girl_head_.blendShape.REyeLidUp": 0,
            "girl_head_.blendShape.REyeMad": 0,
            "girl_head_.blendShape.REyeSad": 0,
            "girl_head_.blendShape.ReyeBSad": 0,
            "girl_head_.blendShape.ReyeBUp": 0,
            "girl_head_.blendShape.ReyeLSad": 0,
            "tgrl1_dmyHeadObjsRoot/tgrl1_logGumTeethAngle/tgrl1_logGumTeethMove/tgrl1_tongue.blendShape.tongue_A": 0,
            "tgrl1_dmyHeadObjsRoot/tgrl1_logGumTeethAngle/tgrl1_logGumTeethMove/tgrl1_tongue.blendShape.tongue_down": 0,
            "tgrl1_dmyHeadObjsRoot/tgrl1_logGumTeethAngle/tgrl1_logGumTeethMove/tgrl1_tongue.blendShape.tongue_F007": 0,
            "tgrl1_dmyHeadObjsRoot/tgrl1_logGumTeethAngle/tgrl1_logGumTeethMove/tgrl1_tongue.blendShape.tongue_F007left": 0,
            "tgrl1_dmyHeadObjsRoot/tgrl1_logGumTeethAngle/tgrl1_logGumTeethMove/tgrl1_tongue.blendShape.tongue_left": 0,
            "tgrl1_dmyHeadObjsRoot/tgrl1_logGumTeethAngle/tgrl1_logGumTeethMove/tgrl1_tongue.blendShape.tongue_O": 0,
            "tgrl1_dmyHeadObjsRoot/tgrl1_logGumTeethAngle/tgrl1_logGumTeethMove/tgrl1_tongue.blendShape.tongue_out": 0,
            "tgrl1_dmyHeadObjsRoot/tgrl1_logGumTeethAngle/tgrl1_logGumTeethMove/tgrl1_tongue.blendShape.tongue_right": 0,
            "tgrl1_dmyHeadObjsRoot/tgrl1_logGumTeethAngle/tgrl1_logGumTeethMove/tgrl1_tongue.blendShape.tongue_up": 0,
            "rig_CharRoot/bip/bip Pelvis/bip Spine/bip Spine1/bip Neck/bip Head/rig_boneTongue.m_LocalPosition.x": -0.0188717656,
            "rig_CharRoot/bip/bip Pelvis/bip Spine/bip Spine1/bip Neck/bip Head/rig_boneTongue.m_LocalPosition.y": 0.0733392909,
            "rig_CharRoot/bip/bip Pelvis/bip Spine/bip Spine1/bip Neck/bip Head/rig_boneTongue.m_LocalPosition.z": 1.52587887E-07,
            "rig_CharRoot/bip/bip Pelvis/bip Spine/bip Spine1/bip Neck/bip Head/rig_boneTongue.localEulerAnglesRaw.x": 178.884003,
            "rig_CharRoot/bip/bip Pelvis/bip Spine/bip Spine1/bip Neck/bip Head/rig_boneTongue.localEulerAnglesRaw.y": 89.9999924,
            "rig_CharRoot/bip/bip Pelvis/bip Spine/bip Spine1/bip Neck/bip Head/rig_boneTongue.localEulerAnglesRaw.z": 0,
            "rig_CharRoot/bip/bip Pelvis/bip Spine/bip Spine1/bip Neck/bip Head/rig_boneTongue.m_LocalScale.x": 1,
            "rig_CharRoot/bip/bip Pelvis/bip Spine/bip Spine1/bip Neck/bip Head/rig_boneTongue.m_LocalScale.y": 1,
            "rig_CharRoot/bip/bip Pelvis/bip Spine/bip Spine1/bip Neck/bip Head/rig_boneTongue.m_LocalScale.z": 1,
            "muscle15": 0,
            "muscle17": 0
          },
          "strings": {},
          "inTangent": 0,
          "inWeight": 0.333333343,
          "outTangent": 0,
          "outWeight": 0.333333343,
          "weightedMode": 0
        }
      ]
    },
    {
      "properties": [
        "Face Animation Neutra"
      ],
      "loops": false,
      "keyFrames": [
        {
          "property": "Face Animation Neutra",
          "index": 0,
          "time": 0,
          "ints": {},
          "floats": {
            "girl_head_.blendShape.mClose": 100,
            "girl_head_.blendShape.A": 0,
            "girl_head_.blendShape.Cons": 0,
            "girl_head_.blendShape.Fv": 0,
            "girl_head_.blendShape.mLSide": 0,
            "girl_head_.blendShape.mLSideUp": 0,
            "girl_head_.blendShape.mRSide": 0,
            "girl_head_.blendShape.mRSideUp": 0,
            "girl_head_.blendShape.O": 0,
            "girl_head_.blendShape.smile": 0,
            "girl_head_.blendShape.U": 0,
            "girl_hair.blendShape.cheek1": 0,
            "girl_hair.blendShape.cheek2": 0,
            "girl_hair.blendShape.cheek3": 0,
            "girl_head_.blendShape.Bmp": 0,
            "girl_head_.blendShape.E": 0,
            "girl_head_.blendShape.F001": 0,
            "girl_head_.blendShape.F003": 0,
            "girl_head_.blendShape.F005": 0,
            "girl_head_.blendShape.F006": 0,
            "girl_head_.blendShape.F007": 0,
            "girl_head_.blendShape.F007left": 0,
            "girl_head_.blendShape.F008": 0,
            "girl_head_.blendShape.F017": 0,
            "girl_head_.blendShape.F019": 0,
            "girl_head_.blendShape.F024": 0,
            "girl_head_.blendShape.F031": 0,
            "girl_head_.blendShape.LEyeBMad": 0,
            "girl_head_.blendShape.LEyeClose": 0,
            "girl_head_.blendShape.LEyeLidUp": 0,
            "girl_head_.blendShape.LEyeMad": 0,
            "girl_head_.blendShape.LEyeSad": 0,
            "girl_head_.blendShape.LeyeBUp": 0,
            "girl_head_.blendShape.mSad": 0,
            "girl_head_.blendShape.REyeBMad": 0,
            "girl_head_.blendShape.REyeClose": 0,
            "girl_head_.blendShape.REyeLidUp": 0,
            "girl_head_.blendShape.REyeMad": 0,
            "girl_head_.blendShape.REyeSad": 0,
            "girl_head_.blendShape.ReyeBSad": 0,
            "girl_head_.blendShape.ReyeBUp": 0,
            "girl_head_.blendShape.ReyeLSad": 0,
            "tgrl1_dmyHeadObjsRoot/tgrl1_logGumTeethAngle/tgrl1_logGumTeethMove/tgrl1_tongue.blendShape.tongue_A": 0,
            "tgrl1_dmyHeadObjsRoot/tgrl1_logGumTeethAngle/tgrl1_logGumTeethMove/tgrl1_tongue.blendShape.tongue_down": 0,
            "tgrl1_dmyHeadObjsRoot/tgrl1_logGumTeethAngle/tgrl1_logGumTeethMove/tgrl1_tongue.blendShape.tongue_F007": 0,
            "tgrl1_dmyHeadObjsRoot/tgrl1_logGumTeethAngle/tgrl1_logGumTeethMove/tgrl1_tongue.blendShape.tongue_F007left": 0,
            "tgrl1_dmyHeadObjsRoot/tgrl1_logGumTeethAngle/tgrl1_logGumTeethMove/tgrl1_tongue.blendShape.tongue_left": 0,
            "tgrl1_dmyHeadObjsRoot/tgrl1_logGumTeethAngle/tgrl1_logGumTeethMove/tgrl1_tongue.blendShape.tongue_O": 0,
            "tgrl1_dmyHeadObjsRoot/tgrl1_logGumTeethAngle/tgrl1_logGumTeethMove/tgrl1_tongue.blendShape.tongue_out": 0,
            "tgrl1_dmyHeadObjsRoot/tgrl1_logGumTeethAngle/tgrl1_logGumTeethMove/tgrl1_tongue.blendShape.tongue_right": 0,
            "tgrl1_dmyHeadObjsRoot/tgrl1_logGumTeethAngle/tgrl1_logGumTeethMove/tgrl1_tongue.blendShape.tongue_up": 0,
            "rig_CharRoot/bip/bip Pelvis/bip Spine/bip Spine1/bip Neck/bip Head/rig_boneTongue.m_LocalPosition.x": -0.0188717656,
            "rig_CharRoot/bip/bip Pelvis/bip Spine/bip Spine1/bip Neck/bip Head/rig_boneTongue.m_LocalPosition.y": 0.0733392909,
            "rig_CharRoot/bip/bip Pelvis/bip Spine/bip Spine1/bip Neck/bip Head/rig_boneTongue.m_LocalPosition.z": 1.52587887E-07,
            "rig_CharRoot/bip/bip Pelvis/bip Spine/bip Spine1/bip Neck/bip Head/rig_boneTongue.localEulerAnglesRaw.x": 178.884003,
            "rig_CharRoot/bip/bip Pelvis/bip Spine/bip Spine1/bip Neck/bip Head/rig_boneTongue.localEulerAnglesRaw.y": 89.9999924,
            "rig_CharRoot/bip/bip Pelvis/bip Spine/bip Spine1/bip Neck/bip Head/rig_boneTongue.localEulerAnglesRaw.z": 0,
            "rig_CharRoot/bip/bip Pelvis/bip Spine/bip Spine1/bip Neck/bip Head/rig_boneTongue.m_LocalScale.x": 1,
            "rig_CharRoot/bip/bip Pelvis/bip Spine/bip Spine1/bip Neck/bip Head/rig_boneTongue.m_LocalScale.y": 1,
            "rig_CharRoot/bip/bip Pelvis/bip Spine/bip Spine1/bip Neck/bip Head/rig_boneTongue.m_LocalScale.z": 1,
            "muscle15": 0,
            "muscle17": 0
          },
          "strings": {},
          "inTangent": 0,
          "inWeight": 0.333333343,
          "outTangent": 0,
          "outWeight": 0.333333343,
          "weightedMode": 0
        }
      ]
    },
    {
      "properties": [
        "Face Animation Neutra"
      ],
      "loops": false,
      "keyFrames": [
        {
          "property": "Face Animation Neutra",
          "index": 0,
          "time": 0,
          "ints": {},
          "floats": {
            "girl_head_.blendShape.mClose": 100,
            "girl_head_.blendShape.A": 0,
            "girl_head_.blendShape.Cons": 0,
            "girl_head_.blendShape.Fv": 0,
            "girl_head_.blendShape.mLSide": 0,
            "girl_head_.blendShape.mLSideUp": 0,
            "girl_head_.blendShape.mRSide": 0,
            "girl_head_.blendShape.mRSideUp": 0,
            "girl_head_.blendShape.O": 0,
            "girl_head_.blendShape.smile": 0,
            "girl_head_.blendShape.U": 0,
            "girl_hair.blendShape.cheek1": 0,
            "girl_hair.blendShape.cheek2": 0,
            "girl_hair.blendShape.cheek3": 0,
            "girl_head_.blendShape.Bmp": 0,
            "girl_head_.blendShape.E": 0,
            "girl_head_.blendShape.F001": 0,
            "girl_head_.blendShape.F003": 0,
            "girl_head_.blendShape.F005": 0,
            "girl_head_.blendShape.F006": 0,
            "girl_head_.blendShape.F007": 0,
            "girl_head_.blendShape.F007left": 0,
            "girl_head_.blendShape.F008": 0,
            "girl_head_.blendShape.F017": 0,
            "girl_head_.blendShape.F019": 0,
            "girl_head_.blendShape.F024": 0,
            "girl_head_.blendShape.F031": 0,
            "girl_head_.blendShape.LEyeBMad": 0,
            "girl_head_.blendShape.LEyeClose": 0,
            "girl_head_.blendShape.LEyeLidUp": 0,
            "girl_head_.blendShape.LEyeMad": 0,
            "girl_head_.blendShape.LEyeSad": 0,
            "girl_head_.blendShape.LeyeBUp": 0,
            "girl_head_.blendShape.mSad": 0,
            "girl_head_.blendShape.REyeBMad": 0,
            "girl_head_.blendShape.REyeClose": 0,
            "girl_head_.blendShape.REyeLidUp": 0,
            "girl_head_.blendShape.REyeMad": 0,
            "girl_head_.blendShape.REyeSad": 0,
            "girl_head_.blendShape.ReyeBSad": 0,
            "girl_head_.blendShape.ReyeBUp": 0,
            "girl_head_.blendShape.ReyeLSad": 0,
            "tgrl1_dmyHeadObjsRoot/tgrl1_logGumTeethAngle/tgrl1_logGumTeethMove/tgrl1_tongue.blendShape.tongue_A": 0,
            "tgrl1_dmyHeadObjsRoot/tgrl1_logGumTeethAngle/tgrl1_logGumTeethMove/tgrl1_tongue.blendShape.tongue_down": 0,
            "tgrl1_dmyHeadObjsRoot/tgrl1_logGumTeethAngle/tgrl1_logGumTeethMove/tgrl1_tongue.blendShape.tongue_F007": 0,
            "tgrl1_dmyHeadObjsRoot/tgrl1_logGumTeethAngle/tgrl1_logGumTeethMove/tgrl1_tongue.blendShape.tongue_F007left": 0,
            "tgrl1_dmyHeadObjsRoot/tgrl1_logGumTeethAngle/tgrl1_logGumTeethMove/tgrl1_tongue.blendShape.tongue_left": 0,
            "tgrl1_dmyHeadObjsRoot/tgrl1_logGumTeethAngle/tgrl1_logGumTeethMove/tgrl1_tongue.blendShape.tongue_O": 0,
            "tgrl1_dmyHeadObjsRoot/tgrl1_logGumTeethAngle/tgrl1_logGumTeethMove/tgrl1_tongue.blendShape.tongue_out": 0,
            "tgrl1_dmyHeadObjsRoot/tgrl1_logGumTeethAngle/tgrl1_logGumTeethMove/tgrl1_tongue.blendShape.tongue_right": 0,
            "tgrl1_dmyHeadObjsRoot/tgrl1_logGumTeethAngle/tgrl1_logGumTeethMove/tgrl1_tongue.blendShape.tongue_up": 0,
            "rig_CharRoot/bip/bip Pelvis/bip Spine/bip Spine1/bip Neck/bip Head/rig_boneTongue.m_LocalPosition.x": -0.0188717656,
            "rig_CharRoot/bip/bip Pelvis/bip Spine/bip Spine1/bip Neck/bip Head/rig_boneTongue.m_LocalPosition.y": 0.0733392909,
            "rig_CharRoot/bip/bip Pelvis/bip Spine/bip Spine1/bip Neck/bip Head/rig_boneTongue.m_LocalPosition.z": 1.52587887E-07,
            "rig_CharRoot/bip/bip Pelvis/bip Spine/bip Spine1/bip Neck/bip Head/rig_boneTongue.localEulerAnglesRaw.x": 178.884003,
            "rig_CharRoot/bip/bip Pelvis/bip Spine/bip Spine1/bip Neck/bip Head/rig_boneTongue.localEulerAnglesRaw.y": 89.9999924,
            "rig_CharRoot/bip/bip Pelvis/bip Spine/bip Spine1/bip Neck/bip Head/rig_boneTongue.localEulerAnglesRaw.z": 0,
            "rig_CharRoot/bip/bip Pelvis/bip Spine/bip Spine1/bip Neck/bip Head/rig_boneTongue.m_LocalScale.x": 1,
            "rig_CharRoot/bip/bip Pelvis/bip Spine/bip Spine1/bip Neck/bip Head/rig_boneTongue.m_LocalScale.y": 1,
            "rig_CharRoot/bip/bip Pelvis/bip Spine/bip Spine1/bip Neck/bip Head/rig_boneTongue.m_LocalScale.z": 1,
            "muscle15": 0,
            "muscle17": 0
          },
          "strings": {},
          "inTangent": 0,
          "inWeight": 0.333333343,
          "outTangent": 0,
          "outWeight": 0.333333343,
          "weightedMode": 0
        }
      ]
    },
    {
      "properties": [
        "Face Animation Neutra"
      ],
      "loops": false,
      "keyFrames": [
        {
          "property": "Face Animation Neutra",
          "index": 0,
          "time": 0,
          "ints": {},
          "floats": {
            "girl_head_.blendShape.mClose": 100,
            "girl_head_.blendShape.A": 0,
            "girl_head_.blendShape.Cons": 0,
            "girl_head_.blendShape.Fv": 0,
            "girl_head_.blendShape.mLSide": 0,
            "girl_head_.blendShape.mLSideUp": 0,
            "girl_head_.blendShape.mRSide": 0,
            "girl_head_.blendShape.mRSideUp": 0,
            "girl_head_.blendShape.O": 0,
            "girl_head_.blendShape.smile": 0,
            "girl_head_.blendShape.U": 0,
            "girl_hair.blendShape.cheek1": 0,
            "girl_hair.blendShape.cheek2": 0,
            "girl_hair.blendShape.cheek3": 0,
            "girl_head_.blendShape.Bmp": 0,
            "girl_head_.blendShape.E": 0,
            "girl_head_.blendShape.F001": 0,
            "girl_head_.blendShape.F003": 0,
            "girl_head_.blendShape.F005": 0,
            "girl_head_.blendShape.F006": 0,
            "girl_head_.blendShape.F007": 0,
            "girl_head_.blendShape.F007left": 0,
            "girl_head_.blendShape.F008": 0,
            "girl_head_.blendShape.F017": 0,
            "girl_head_.blendShape.F019": 0,
            "girl_head_.blendShape.F024": 0,
            "girl_head_.blendShape.F031": 0,
            "girl_head_.blendShape.LEyeBMad": 0,
            "girl_head_.blendShape.LEyeClose": 0,
            "girl_head_.blendShape.LEyeLidUp": 0,
            "girl_head_.blendShape.LEyeMad": 0,
            "girl_head_.blendShape.LEyeSad": 0,
            "girl_head_.blendShape.LeyeBUp": 0,
            "girl_head_.blendShape.mSad": 0,
            "girl_head_.blendShape.REyeBMad": 0,
            "girl_head_.blendShape.REyeClose": 0,
            "girl_head_.blendShape.REyeLidUp": 0,
            "girl_head_.blendShape.REyeMad": 0,
            "girl_head_.blendShape.REyeSad": 0,
            "girl_head_.blendShape.ReyeBSad": 0,
            "girl_head_.blendShape.ReyeBUp": 0,
            "girl_head_.blendShape.ReyeLSad": 0,
            "tgrl1_dmyHeadObjsRoot/tgrl1_logGumTeethAngle/tgrl1_logGumTeethMove/tgrl1_tongue.blendShape.tongue_A": 0,
            "tgrl1_dmyHeadObjsRoot/tgrl1_logGumTeethAngle/tgrl1_logGumTeethMove/tgrl1_tongue.blendShape.tongue_down": 0,
            "tgrl1_dmyHeadObjsRoot/tgrl1_logGumTeethAngle/tgrl1_logGumTeethMove/tgrl1_tongue.blendShape.tongue_F007": 0,
            "tgrl1_dmyHeadObjsRoot/tgrl1_logGumTeethAngle/tgrl1_logGumTeethMove/tgrl1_tongue.blendShape.tongue_F007left": 0,
            "tgrl1_dmyHeadObjsRoot/tgrl1_logGumTeethAngle/tgrl1_logGumTeethMove/tgrl1_tongue.blendShape.tongue_left": 0,
            "tgrl1_dmyHeadObjsRoot/tgrl1_logGumTeethAngle/tgrl1_logGumTeethMove/tgrl1_tongue.blendShape.tongue_O": 0,
            "tgrl1_dmyHeadObjsRoot/tgrl1_logGumTeethAngle/tgrl1_logGumTeethMove/tgrl1_tongue.blendShape.tongue_out": 0,
            "tgrl1_dmyHeadObjsRoot/tgrl1_logGumTeethAngle/tgrl1_logGumTeethMove/tgrl1_tongue.blendShape.tongue_right": 0,
            "tgrl1_dmyHeadObjsRoot/tgrl1_logGumTeethAngle/tgrl1_logGumTeethMove/tgrl1_tongue.blendShape.tongue_up": 0,
            "rig_CharRoot/bip/bip Pelvis/bip Spine/bip Spine1/bip Neck/bip Head/rig_boneTongue.m_LocalPosition.x": -0.0188717656,
            "rig_CharRoot/bip/bip Pelvis/bip Spine/bip Spine1/bip Neck/bip Head/rig_boneTongue.m_LocalPosition.y": 0.0733392909,
            "rig_CharRoot/bip/bip Pelvis/bip Spine/bip Spine1/bip Neck/bip Head/rig_boneTongue.m_LocalPosition.z": 1.52587887E-07,
            "rig_CharRoot/bip/bip Pelvis/bip Spine/bip Spine1/bip Neck/bip Head/rig_boneTongue.localEulerAnglesRaw.x": 178.884003,
            "rig_CharRoot/bip/bip Pelvis/bip Spine/bip Spine1/bip Neck/bip Head/rig_boneTongue.localEulerAnglesRaw.y": 89.9999924,
            "rig_CharRoot/bip/bip Pelvis/bip Spine/bip Spine1/bip Neck/bip Head/rig_boneTongue.localEulerAnglesRaw.z": 0,
            "rig_CharRoot/bip/bip Pelvis/bip Spine/bip Spine1/bip Neck/bip Head/rig_boneTongue.m_LocalScale.x": 1,
            "rig_CharRoot/bip/bip Pelvis/bip Spine/bip Spine1/bip Neck/bip Head/rig_boneTongue.m_LocalScale.y": 1,
            "rig_CharRoot/bip/bip Pelvis/bip Spine/bip Spine1/bip Neck/bip Head/rig_boneTongue.m_LocalScale.z": 1,
            "muscle15": 0,
            "muscle17": 0
          },
          "strings": {},
          "inTangent": 0,
          "inWeight": 0.333333343,
          "outTangent": 0,
          "outWeight": 0.333333343,
          "weightedMode": 0
        }
      ]
    }
  ],
  "linguisticTags": {},
  "version": 12,
  "globalSpeed": 1,
  "globalRepetitions": 1
}
