{
  "animTracks": [
    {
      "properties": [
        "Right Hand Configuration",
        "Left Hand Configuration",
        "Muscles",
        "Facial Expression"
      ],
      "loops": false,
      "keyFrames": [
        {
          "property": "Muscles",
          "index": 3,
          "time": 6.17676783,
          "ints": {},
          "floats": {
            "muscle0": 2.1398753E-12,
            "muscle1": -4.07110923E-13,
            "muscle2": -9.56710622E-13,
            "muscle3": -1.48849899E-12,
            "muscle4": -1.69222731E-25,
            "muscle5": -3.25688776E-13,
            "muscle6": 0,
            "muscle7": 0,
            "muscle8": 0,
            "muscle9": -3.96933029E-13,
            "muscle10": -4.0711097E-14,
            "muscle11": -3.25688776E-13,
            "muscle12": 1.06721654E-06,
            "muscle13": 5.19687489E-07,
            "muscle14": 4.30784581E-08,
            "muscle15": 0,
            "muscle16": -3.13225756E-09,
            "muscle17": 0,
            "muscle18": -2.60550999E-12,
            "muscle19": 0,
            "muscle20": 0,
            "muscle21": 0.520543635,
            "muscle22": -0.0643745139,
            "muscle23": -0.236130282,
            "muscle24": 0.924838722,
            "muscle25": 0.190328777,
            "muscle26": -0.0649203956,
            "muscle27": 0.0751548186,
            "muscle28": 1.19461595E-06,
            "muscle29": 0.520541847,
            "muscle30": -0.0643770918,
            "muscle31": -0.236131653,
            "muscle32": 0.924839139,
            "muscle33": 0.190330312,
            "muscle34": -0.0648726523,
            "muscle35": 0.0751641393,
            "muscle36": 9.46487944E-07,
            "muscle37": -0.499998987,
            "muscle38": 0.00360289821,
            "muscle39": -0.516910195,
            "muscle40": 0.211185247,
            "muscle41": -0.0540147312,
            "muscle42": 0.984187365,
            "muscle43": 0.152994022,
            "muscle44": -0.0189265236,
            "muscle45": 0.0221466683,
            "muscle46": -0.499998987,
            "muscle47": 0.00360562769,
            "muscle48": 0.0202246644,
            "muscle49": 0.157657608,
            "muscle50": -0.152334467,
            "muscle51": -0.474892139,
            "muscle52": 0.573433101,
            "muscle53": -0.543531656,
            "muscle54": 1.00181937,
            "muscle55": -1.017777E-14,
            "muscle56": 1.36603745E-07,
            "muscle57": 3.64950097E-08,
            "muscle58": 9.11422333E-08,
            "muscle59": -6.83018726E-08,
            "muscle60": 8.53773443E-08,
            "muscle61": -7.58909735E-08,
            "muscle62": -2.20871803E-18,
            "muscle63": 2.39056618E-07,
            "muscle64": 5.93703519E-15,
            "muscle65": -7.58909806E-08,
            "muscle66": -4.55345855E-07,
            "muscle67": 3.41509399E-08,
            "muscle68": -1.13836471E-07,
            "muscle69": -6.07127788E-07,
            "muscle70": -2.76089676E-19,
            "muscle71": -4.78113179E-07,
            "muscle72": 0,
            "muscle73": 1.51781947E-07,
            "muscle74": 0,
            "muscle75": -1.09020829,
            "muscle76": -0.527778864,
            "muscle77": 0.6399948,
            "muscle78": 0.999999821,
            "muscle79": 0.0444443449,
            "muscle80": 0.2575275,
            "muscle81": 0.511528969,
            "muscle82": 1.00000012,
            "muscle83": -0.822222412,
            "muscle84": -0.436818182,
            "muscle85": 0.433333665,
            "muscle86": 0.840000153,
            "muscle87": 0.0409534983,
            "muscle88": -0.350675583,
            "muscle89": 0.44426766,
            "muscle90": 0.799999952,
            "muscle91": 0.511449516,
            "muscle92": 0.508948684,
            "muscle93": 0.666666806,
            "muscle94": 0.666666746,
            "duration": 0,
            "muscle-1": 1
          },
          "strings": {
            "interpolation": "default"
          },
          "inTangent": 0,
          "inWeight": 0,
          "outTangent": 0,
          "outWeight": 0,
          "weightedMode": 0
        },
        {
          "property": "Muscles",
          "index": 2,
          "time": 5.66666746,
          "ints": {},
          "floats": {
            "muscle0": 2.1398753E-12,
            "muscle1": -4.07110923E-13,
            "muscle2": -9.56710622E-13,
            "muscle3": -1.48849899E-12,
            "muscle4": -1.69222731E-25,
            "muscle5": -3.25688776E-13,
            "muscle6": 0,
            "muscle7": 0,
            "muscle8": 0,
            "muscle9": -3.96933029E-13,
            "muscle10": -4.0711097E-14,
            "muscle11": -3.25688776E-13,
            "muscle12": 1.06721654E-06,
            "muscle13": 5.69452112E-08,
            "muscle14": -7.37964001E-08,
            "muscle15": 0,
            "muscle16": -3.13225756E-09,
            "muscle17": 0,
            "muscle18": -2.60550999E-12,
            "muscle19": 0,
            "muscle20": 0,
            "muscle21": 0.520542502,
            "muscle22": -0.0643762201,
            "muscle23": -0.236129537,
            "muscle24": 0.924838662,
            "muscle25": 0.190328792,
            "muscle26": -0.0649192184,
            "muscle27": 0.0751575083,
            "muscle28": 1.19461595E-06,
            "muscle29": 0.52053988,
            "muscle30": -0.0643784851,
            "muscle31": -0.236129954,
            "muscle32": 0.924839139,
            "muscle33": 0.190329701,
            "muscle34": -0.0648701638,
            "muscle35": 0.0751669928,
            "muscle36": 1.94633657E-07,
            "muscle37": -0.499997884,
            "muscle38": 0.00360333174,
            "muscle39": -0.516915739,
            "muscle40": 0.211188063,
            "muscle41": -0.0540152602,
            "muscle42": 0.984187365,
            "muscle43": 0.152994275,
            "muscle44": -0.0189229529,
            "muscle45": 0.0221401043,
            "muscle46": -0.499998987,
            "muscle47": 0.00360562769,
            "muscle48": 0.015275823,
            "muscle49": 0.0875091851,
            "muscle50": -0.130792469,
            "muscle51": -0.350193322,
            "muscle52": 0.571430266,
            "muscle53": -0.351579696,
            "muscle54": 1.00184023,
            "muscle55": -1.017777E-14,
            "muscle56": 1.36603745E-07,
            "muscle57": 3.64950097E-08,
            "muscle58": 9.11422333E-08,
            "muscle59": -6.83018726E-08,
            "muscle60": 8.53773443E-08,
            "muscle61": -7.58909735E-08,
            "muscle62": -2.20871803E-18,
            "muscle63": 6.83018939E-08,
            "muscle64": -2.2767297E-07,
            "muscle65": -7.58909806E-08,
            "muscle66": 4.96961642E-17,
            "muscle67": 3.41509399E-08,
            "muscle68": -1.13836471E-07,
            "muscle69": -1.51781947E-07,
            "muscle70": -2.76089676E-19,
            "muscle71": -4.78113179E-07,
            "muscle72": 0,
            "muscle73": 1.51781947E-07,
            "muscle74": 0,
            "muscle75": -1.09020841,
            "muscle76": -0.527778983,
            "muscle77": 0.6399948,
            "muscle78": 0.999999821,
            "muscle79": 0.0444443449,
            "muscle80": 0.2575275,
            "muscle81": 0.511528969,
            "muscle82": 1.00000012,
            "muscle83": -0.822222531,
            "muscle84": -0.436818272,
            "muscle85": 0.433333665,
            "muscle86": 0.840000153,
            "muscle87": 0.0409532972,
            "muscle88": -0.350675583,
            "muscle89": 0.44426766,
            "muscle90": 0.799999952,
            "muscle91": 0.511449516,
            "muscle92": 0.508948684,
            "muscle93": 0.666666806,
            "muscle94": 0.666666746,
            "duration": 0,
            "muscle-1": 1
          },
          "strings": {
            "interpolation": "default"
          },
          "inTangent": 0,
          "inWeight": 0,
          "outTangent": 0,
          "outWeight": 0,
          "weightedMode": 0
        },
        {
          "property": "Muscles",
          "index": 1,
          "time": 5.11616135,
          "ints": {},
          "floats": {
            "muscle0": 2.1398753E-12,
            "muscle1": -4.07110923E-13,
            "muscle2": -9.56710622E-13,
            "muscle3": -1.48849899E-12,
            "muscle4": -1.69222731E-25,
            "muscle5": -3.25688776E-13,
            "muscle6": 0,
            "muscle7": 0,
            "muscle8": 0,
            "muscle9": -3.96933029E-13,
            "muscle10": -4.0711097E-14,
            "muscle11": -3.25688776E-13,
            "muscle12": 5.54952521E-07,
            "muscle13": 1.90482581E-07,
            "muscle14": -1.50335708E-07,
            "muscle15": 0,
            "muscle16": 9.75310357E-08,
            "muscle17": 0,
            "muscle18": -2.60550999E-12,
            "muscle19": 0,
            "muscle20": 0,
            "muscle21": 0.522002518,
            "muscle22": -0.0674787834,
            "muscle23": -0.308532596,
            "muscle24": 0.930870712,
            "muscle25": 0.238751888,
            "muscle26": -0.0638652816,
            "muscle27": 0.0695130005,
            "muscle28": 1.19461595E-06,
            "muscle29": 0.522000849,
            "muscle30": -0.0674816221,
            "muscle31": -0.308533728,
            "muscle32": 0.930870771,
            "muscle33": 0.238753468,
            "muscle34": -0.0638173744,
            "muscle35": 0.0695223957,
            "muscle36": 8.09750759E-07,
            "muscle37": -0.499998987,
            "muscle38": 0.00360289821,
            "muscle39": -0.515925229,
            "muscle40": 0.211085722,
            "muscle41": -0.0779902786,
            "muscle42": 0.985978901,
            "muscle43": 0.176828146,
            "muscle44": -0.0182131082,
            "muscle45": 0.021788545,
            "muscle46": -0.499998987,
            "muscle47": 0.00360562769,
            "muscle48": 0.0205272026,
            "muscle49": 0.157521084,
            "muscle50": -0.152604491,
            "muscle51": -0.474827886,
            "muscle52": 0.573604524,
            "muscle53": -0.543245316,
            "muscle54": 1.00107563,
            "muscle55": -1.017777E-14,
            "muscle56": 1.36603745E-07,
            "muscle57": 3.64950097E-08,
            "muscle58": 9.11422333E-08,
            "muscle59": -6.83018726E-08,
            "muscle60": 8.53773443E-08,
            "muscle61": -7.58909735E-08,
            "muscle62": -2.20871803E-18,
            "muscle63": 2.39056618E-07,
            "muscle64": 5.93703519E-15,
            "muscle65": -7.58909806E-08,
            "muscle66": -4.55345855E-07,
            "muscle67": 3.41509399E-08,
            "muscle68": -1.13836471E-07,
            "muscle69": -6.07127788E-07,
            "muscle70": -2.76089676E-19,
            "muscle71": -4.78113179E-07,
            "muscle72": 0,
            "muscle73": 1.51781947E-07,
            "muscle74": 0,
            "muscle75": -1.09020841,
            "muscle76": -0.527778983,
            "muscle77": 0.6399948,
            "muscle78": 0.999999821,
            "muscle79": 0.0444443449,
            "muscle80": 0.2575275,
            "muscle81": 0.511528969,
            "muscle82": 1.00000012,
            "muscle83": -0.822222412,
            "muscle84": -0.436818182,
            "muscle85": 0.433333486,
            "muscle86": 0.840000153,
            "muscle87": 0.0409534983,
            "muscle88": -0.350675583,
            "muscle89": 0.44426766,
            "muscle90": 0.799999952,
            "muscle91": 0.511449516,
            "muscle92": 0.508948684,
            "muscle93": 0.666666806,
            "muscle94": 0.666666746,
            "duration": 0,
            "muscle-1": 1
          },
          "strings": {
            "interpolation": "default"
          },
          "inTangent": 0,
          "inWeight": 0,
          "outTangent": 0,
          "outWeight": 0,
          "weightedMode": 0
        },
        {
          "property": "Muscles",
          "index": 5,
          "time": 1.01515138,
          "ints": {},
          "floats": {
            "muscle0": 2.1398753E-12,
            "muscle1": -4.07110923E-13,
            "muscle2": -9.56710622E-13,
            "muscle3": -1.48849899E-12,
            "muscle4": -1.69222731E-25,
            "muscle5": -3.25688776E-13,
            "muscle6": 0,
            "muscle7": 0,
            "muscle8": 0,
            "muscle9": -3.96933029E-13,
            "muscle10": -4.0711097E-14,
            "muscle11": -3.25688776E-13,
            "muscle12": 2.98820453E-07,
            "muscle13": 2.69903552E-07,
            "muscle14": -5.93909668E-08,
            "muscle15": 0,
            "muscle16": -3.13225756E-09,
            "muscle17": 0,
            "muscle18": -2.60550999E-12,
            "muscle19": 0,
            "muscle20": 0,
            "muscle21": 0.52423346,
            "muscle22": -0.0713517517,
            "muscle23": -0.415073454,
            "muscle24": 0.939663827,
            "muscle25": 0.309935927,
            "muscle26": -0.0621738322,
            "muscle27": 0.0624387264,
            "muscle28": 3.74593156E-07,
            "muscle29": 0.52423209,
            "muscle30": -0.0713537261,
            "muscle31": -0.415079117,
            "muscle32": 0.93966347,
            "muscle33": 0.309940219,
            "muscle34": -0.062127836,
            "muscle35": 0.0624450967,
            "muscle36": 3.996727E-07,
            "muscle37": -0.499999434,
            "muscle38": 0.00360223628,
            "muscle39": -0.514535487,
            "muscle40": 0.210907057,
            "muscle41": -0.1139699,
            "muscle42": 0.988652945,
            "muscle43": 0.2126147,
            "muscle44": -0.0172159839,
            "muscle45": 0.021216752,
            "muscle46": -0.499997675,
            "muscle47": 0.00360540743,
            "muscle48": -0.0248062033,
            "muscle49": 0.107686445,
            "muscle50": -0.172291324,
            "muscle51": -0.587722898,
            "muscle52": 0.576260746,
            "muscle53": -0.543074965,
            "muscle54": 1.00061083,
            "muscle55": -1.017777E-14,
            "muscle56": 1.36603745E-07,
            "muscle57": 3.64950097E-08,
            "muscle58": 9.11422333E-08,
            "muscle59": -6.83018726E-08,
            "muscle60": 8.53773443E-08,
            "muscle61": -7.58909735E-08,
            "muscle62": -2.20871803E-18,
            "muscle63": 6.83018939E-08,
            "muscle64": -2.2767297E-07,
            "muscle65": -7.58909806E-08,
            "muscle66": 4.96961642E-17,
            "muscle67": 3.41509399E-08,
            "muscle68": -1.13836471E-07,
            "muscle69": -6.07127788E-07,
            "muscle70": -2.76089676E-19,
            "muscle71": -4.78113179E-07,
            "muscle72": 0,
            "muscle73": 1.51781947E-07,
            "muscle74": 0,
            "muscle75": -0.156874686,
            "muscle76": 0.505554259,
            "muscle77": 0.6399948,
            "muscle78": 0.639995337,
            "muscle79": 0.553255916,
            "muscle80": 0.288638234,
            "muscle81": 0.77819556,
            "muscle82": 0.77819562,
            "muscle83": 0.665139318,
            "muscle84": -0.436818361,
            "muscle85": 0.804009497,
            "muscle86": 0.804009497,
            "muscle87": 0.640953422,
            "muscle88": 0.271548092,
            "muscle89": 0.810934067,
            "muscle90": 0.810933948,
            "muscle91": 0.578116179,
            "muscle92": 0.695615232,
            "muscle93": 0.811357141,
            "muscle94": 0.811358154,
            "duration": 0,
            "muscle-1": 1
          },
          "strings": {
            "interpolation": "default"
          },
          "inTangent": 0,
          "inWeight": 0,
          "outTangent": 0,
          "outWeight": 0,
          "weightedMode": 0
        },
        {
          "property": "Muscles",
          "index": 6,
          "time": 1.74242413,
          "ints": {},
          "floats": {
            "muscle0": 2.15925563E-12,
            "muscle1": 2.68220703E-07,
            "muscle2": -2.03555451E-14,
            "muscle3": -1.48849899E-12,
            "muscle4": -1.69222731E-25,
            "muscle5": -3.25688776E-13,
            "muscle6": 0,
            "muscle7": 0,
            "muscle8": 0,
            "muscle9": -3.96933029E-13,
            "muscle10": -4.0711097E-14,
            "muscle11": -3.25688776E-13,
            "muscle12": 6.40329915E-07,
            "muscle13": -4.67929908E-07,
            "muscle14": -5.37164226E-07,
            "muscle15": 0,
            "muscle16": -3.13225756E-09,
            "muscle17": 0,
            "muscle18": -2.60550999E-12,
            "muscle19": 0,
            "muscle20": 0,
            "muscle21": 0.519556582,
            "muscle22": -0.0619091541,
            "muscle23": -0.18409808,
            "muscle24": 0.920473397,
            "muscle25": 0.155513048,
            "muscle26": -0.0655943751,
            "muscle27": 0.0796488002,
            "muscle28": 2.37989369E-07,
            "muscle29": 0.519555748,
            "muscle30": -0.0619052462,
            "muscle31": -0.18410404,
            "muscle32": 0.920473099,
            "muscle33": 0.15551585,
            "muscle34": -0.0655483827,
            "muscle35": 0.0796466917,
            "muscle36": 3.996727E-07,
            "muscle37": -0.499998927,
            "muscle38": 0.00360587891,
            "muscle39": -0.506332338,
            "muscle40": 0.20404461,
            "muscle41": -0.137267768,
            "muscle42": 1.00215685,
            "muscle43": 0.233567119,
            "muscle44": -0.0358515419,
            "muscle45": 0.0585609823,
            "muscle46": -0.499997675,
            "muscle47": 0.00360633456,
            "muscle48": -0.128948689,
            "muscle49": 0.445308685,
            "muscle50": -0.143873021,
            "muscle51": -0.627752006,
            "muscle52": 0.458612919,
            "muscle53": -0.421458721,
            "muscle54": 0.608819783,
            "muscle55": -1.02452827E-06,
            "muscle56": 2.80037671E-06,
            "muscle57": 3.64950097E-08,
            "muscle58": 9.11422333E-08,
            "muscle59": -6.83018726E-08,
            "muscle60": 8.53773443E-08,
            "muscle61": -7.58909735E-08,
            "muscle62": -2.20871803E-18,
            "muscle63": 6.83018939E-08,
            "muscle64": -2.2767297E-07,
            "muscle65": -4.55345855E-07,
            "muscle66": 4.96961642E-17,
            "muscle67": 3.41509399E-08,
            "muscle68": -1.13836471E-07,
            "muscle69": -6.07127788E-07,
            "muscle70": -2.76089676E-19,
            "muscle71": -4.78113179E-07,
            "muscle72": 0,
            "muscle73": 1.51781947E-07,
            "muscle74": 0,
            "muscle75": -0.156874686,
            "muscle76": 0.505554259,
            "muscle77": 0.6399948,
            "muscle78": 0.639995337,
            "muscle79": 0.553255916,
            "muscle80": 0.288637817,
            "muscle81": 0.77819556,
            "muscle82": 0.77819562,
            "muscle83": 0.665139318,
            "muscle84": -0.436818361,
            "muscle85": 0.804009497,
            "muscle86": 0.804009497,
            "muscle87": 0.640953422,
            "muscle88": 0.271548092,
            "muscle89": 0.810934067,
            "muscle90": 0.810933828,
            "muscle91": 0.578116179,
            "muscle92": 0.695615232,
            "muscle93": 0.811356843,
            "muscle94": 0.811357141,
            "duration": 0,
            "muscle-1": 1
          },
          "strings": {
            "interpolation": "smooth"
          },
          "inTangent": 0,
          "inWeight": 0,
          "outTangent": 0,
          "outWeight": 0,
          "weightedMode": 0
        },
        {
          "property": "Muscles",
          "index": 7,
          "time": 2.53535318,
          "ints": {},
          "floats": {
            "muscle0": 2.15925563E-12,
            "muscle1": 2.68220703E-07,
            "muscle2": -2.03555451E-14,
            "muscle3": -1.48849899E-12,
            "muscle4": -1.69222731E-25,
            "muscle5": -3.25688776E-13,
            "muscle6": 0,
            "muscle7": 0,
            "muscle8": 0,
            "muscle9": -3.96933029E-13,
            "muscle10": -4.0711097E-14,
            "muscle11": -3.25688776E-13,
            "muscle12": 1.06721654E-06,
            "muscle13": 1.36365657E-07,
            "muscle14": 1.71483041E-08,
            "muscle15": 0,
            "muscle16": 9.56501296E-08,
            "muscle17": 0,
            "muscle18": -2.60550999E-12,
            "muscle19": 0,
            "muscle20": 0,
            "muscle21": 0.520542562,
            "muscle22": -0.0643858984,
            "muscle23": -0.236124933,
            "muscle24": 0.924839318,
            "muscle25": 0.190327689,
            "muscle26": -0.064918384,
            "muscle27": 0.0751777142,
            "muscle28": 3.74593156E-07,
            "muscle29": 0.520541072,
            "muscle30": -0.0643766969,
            "muscle31": -0.236132726,
            "muscle32": 0.924838781,
            "muscle33": 0.190330744,
            "muscle34": -0.0648732632,
            "muscle35": 0.0751642212,
            "muscle36": 8.09750759E-07,
            "muscle37": -0.499998987,
            "muscle38": 0.00360380346,
            "muscle39": -0.50460273,
            "muscle40": 0.203725606,
            "muscle41": -0.227296814,
            "muscle42": 1.00882447,
            "muscle43": 0.323302358,
            "muscle44": -0.0192869511,
            "muscle45": 0.0229775421,
            "muscle46": -0.499997675,
            "muscle47": 0.00360633456,
            "muscle48": 0.0341638029,
            "muscle49": 0.0584561713,
            "muscle50": -0.536023498,
            "muscle51": -0.451159805,
            "muscle52": 0.207593545,
            "muscle53": -0.380870432,
            "muscle54": 1.00041497,
            "muscle55": -1.70754717E-07,
            "muscle56": 1.36603762E-06,
            "muscle57": 3.64950097E-08,
            "muscle58": 9.11422333E-08,
            "muscle59": -6.83018726E-08,
            "muscle60": 8.53773443E-08,
            "muscle61": -7.58909735E-08,
            "muscle62": -2.20871803E-18,
            "muscle63": 6.83018939E-08,
            "muscle64": -2.2767297E-07,
            "muscle65": -4.55345855E-07,
            "muscle66": 4.96961642E-17,
            "muscle67": 3.41509399E-08,
            "muscle68": -1.13836471E-07,
            "muscle69": -1.51781947E-07,
            "muscle70": -2.76089676E-19,
            "muscle71": -3.41509399E-08,
            "muscle72": 4.26886793E-08,
            "muscle73": 3.03563922E-07,
            "muscle74": 0,
            "muscle75": -0.156874686,
            "muscle76": 0.505554259,
            "muscle77": 0.6399948,
            "muscle78": 0.639995337,
            "muscle79": 0.553255916,
            "muscle80": 0.288638234,
            "muscle81": 0.77819556,
            "muscle82": 0.77819562,
            "muscle83": 0.665139318,
            "muscle84": -0.436818361,
            "muscle85": 0.804009497,
            "muscle86": 0.804009497,
            "muscle87": 0.640953422,
            "muscle88": 0.271548092,
            "muscle89": 0.810934067,
            "muscle90": 0.810933828,
            "muscle91": 0.578116179,
            "muscle92": 0.695615232,
            "muscle93": 0.811356843,
            "muscle94": 0.811357796,
            "duration": 0,
            "muscle-1": 1
          },
          "strings": {
            "interpolation": "smooth"
          },
          "inTangent": 0,
          "inWeight": 0,
          "outTangent": 0,
          "outWeight": 0,
          "weightedMode": 0
        },
        {
          "property": "Muscles",
          "index": 8,
          "time": 3.25252581,
          "ints": {},
          "floats": {
            "muscle0": 2.1398753E-12,
            "muscle1": -4.07110923E-13,
            "muscle2": -9.56710622E-13,
            "muscle3": -1.48849899E-12,
            "muscle4": -1.69222731E-25,
            "muscle5": -3.25688776E-13,
            "muscle6": 0,
            "muscle7": 0,
            "muscle8": 0,
            "muscle9": -3.96933029E-13,
            "muscle10": -4.0711097E-14,
            "muscle11": -3.25688776E-13,
            "muscle12": 5.76296884E-07,
            "muscle13": -7.65898278E-08,
            "muscle14": 2.74273826E-09,
            "muscle15": 0,
            "muscle16": 9.75310357E-08,
            "muscle17": 0,
            "muscle18": -2.60550999E-12,
            "muscle19": 0,
            "muscle20": 0,
            "muscle21": 0.522004902,
            "muscle22": -0.0674874187,
            "muscle23": -0.308529526,
            "muscle24": 0.930871248,
            "muscle25": 0.238751784,
            "muscle26": -0.0638662726,
            "muscle27": 0.0695305914,
            "muscle28": 3.74593156E-07,
            "muscle29": 0.522003114,
            "muscle30": -0.0674887151,
            "muscle31": -0.308531046,
            "muscle32": 0.930870771,
            "muscle33": 0.238753036,
            "muscle34": -0.0638194159,
            "muscle35": 0.0695372522,
            "muscle36": 3.996727E-07,
            "muscle37": -0.499998987,
            "muscle38": 0.00360289821,
            "muscle39": -0.515922666,
            "muscle40": 0.211079106,
            "muscle41": -0.0779861212,
            "muscle42": 0.985978961,
            "muscle43": 0.176825315,
            "muscle44": -0.0182145461,
            "muscle45": 0.0218034592,
            "muscle46": -0.499998987,
            "muscle47": 0.00360562769,
            "muscle48": -0.126380354,
            "muscle49": -0.0429749452,
            "muscle50": -0.444699526,
            "muscle51": -0.439075977,
            "muscle52": 0.463054478,
            "muscle53": -0.279328436,
            "muscle54": 1.00077116,
            "muscle55": -1.70754717E-07,
            "muscle56": 5.46414981E-07,
            "muscle57": 3.64950097E-08,
            "muscle58": 9.11422333E-08,
            "muscle59": -6.83018726E-08,
            "muscle60": 8.53773443E-08,
            "muscle61": -7.58909735E-08,
            "muscle62": -2.20871803E-18,
            "muscle63": 6.83018939E-08,
            "muscle64": -2.2767297E-07,
            "muscle65": -7.58909806E-08,
            "muscle66": 4.96961642E-17,
            "muscle67": 3.41509399E-08,
            "muscle68": -1.13836471E-07,
            "muscle69": -1.51781947E-07,
            "muscle70": -2.76089676E-19,
            "muscle71": -3.41509399E-08,
            "muscle72": 4.26886793E-08,
            "muscle73": 3.03563922E-07,
            "muscle74": -5.31236935E-07,
            "muscle75": -0.156874686,
            "muscle76": 0.505554259,
            "muscle77": 0.6399948,
            "muscle78": 0.639995337,
            "muscle79": 0.553255916,
            "muscle80": 0.288638234,
            "muscle81": 0.77819556,
            "muscle82": 0.77819562,
            "muscle83": 0.665139318,
            "muscle84": -0.436818361,
            "muscle85": 0.804009497,
            "muscle86": 0.804009497,
            "muscle87": 0.640953422,
            "muscle88": 0.271548092,
            "muscle89": 0.810934067,
            "muscle90": 0.810933828,
            "muscle91": 0.578116179,
            "muscle92": 0.695615232,
            "muscle93": 0.811357141,
            "muscle94": 0.811358154,
            "duration": 0,
            "muscle-1": 1
          },
          "strings": {
            "interpolation": "smooth"
          },
          "inTangent": 0,
          "inWeight": 0,
          "outTangent": 0,
          "outWeight": 0,
          "weightedMode": 0
        },
        {
          "property": "Muscles",
          "index": 9,
          "time": 3.92424297,
          "ints": {},
          "floats": {
            "muscle0": 2.1398753E-12,
            "muscle1": -4.07110923E-13,
            "muscle2": -9.56710622E-13,
            "muscle3": -1.48849899E-12,
            "muscle4": -1.69222731E-25,
            "muscle5": -3.25688776E-13,
            "muscle6": 0,
            "muscle7": 0,
            "muscle8": 0,
            "muscle9": -3.96933029E-13,
            "muscle10": -4.0711097E-14,
            "muscle11": -3.25688776E-13,
            "muscle12": 1.92098767E-07,
            "muscle13": -3.39977539E-08,
            "muscle14": 5.62391866E-09,
            "muscle15": 0,
            "muscle16": -3.13225756E-09,
            "muscle17": 0,
            "muscle18": -2.60550999E-12,
            "muscle19": 0,
            "muscle20": 0,
            "muscle21": 0.52422893,
            "muscle22": -0.0713485181,
            "muscle23": -0.415078372,
            "muscle24": 0.939663649,
            "muscle25": 0.309938967,
            "muscle26": -0.0621704683,
            "muscle27": 0.0624307953,
            "muscle28": 8.52839719E-07,
            "muscle29": 0.524227202,
            "muscle30": -0.0713513568,
            "muscle31": -0.415079147,
            "muscle32": 0.93966341,
            "muscle33": 0.309940398,
            "muscle34": -0.0621230155,
            "muscle35": 0.0624397509,
            "muscle36": 3.996727E-07,
            "muscle37": -0.499998987,
            "muscle38": 0.00360289821,
            "muscle39": -0.514534831,
            "muscle40": 0.2109081,
            "muscle41": -0.113969788,
            "muscle42": 0.988652766,
            "muscle43": 0.212614089,
            "muscle44": -0.0172167998,
            "muscle45": 0.0212144107,
            "muscle46": -0.499998987,
            "muscle47": 0.00360562769,
            "muscle48": -0.0248051919,
            "muscle49": 0.107679181,
            "muscle50": -0.172282979,
            "muscle51": -0.587723255,
            "muscle52": 0.576272845,
            "muscle53": -0.543072104,
            "muscle54": 1.00063097,
            "muscle55": -1.017777E-14,
            "muscle56": 1.36603745E-07,
            "muscle57": 3.64950097E-08,
            "muscle58": 9.11422333E-08,
            "muscle59": -6.83018726E-08,
            "muscle60": 8.53773443E-08,
            "muscle61": -7.58909735E-08,
            "muscle62": -2.20871803E-18,
            "muscle63": 2.39056618E-07,
            "muscle64": 5.93703519E-15,
            "muscle65": -7.58909806E-08,
            "muscle66": -4.55345855E-07,
            "muscle67": 3.41509399E-08,
            "muscle68": -1.13836471E-07,
            "muscle69": -6.07127788E-07,
            "muscle70": -2.76089676E-19,
            "muscle71": -4.78113179E-07,
            "muscle72": 0,
            "muscle73": 1.51781947E-07,
            "muscle74": 0,
            "muscle75": -0.156874686,
            "muscle76": 0.505554259,
            "muscle77": 0.6399948,
            "muscle78": 0.639995337,
            "muscle79": 0.553255916,
            "muscle80": 0.288638234,
            "muscle81": 0.77819556,
            "muscle82": 0.77819562,
            "muscle83": 0.665139318,
            "muscle84": -0.436818361,
            "muscle85": 0.804009497,
            "muscle86": 0.804009497,
            "muscle87": 0.640953422,
            "muscle88": 0.271548092,
            "muscle89": 0.810934067,
            "muscle90": 0.810933948,
            "muscle91": 0.578116179,
            "muscle92": 0.695615232,
            "muscle93": 0.811357141,
            "muscle94": 0.811358154,
            "duration": 0,
            "muscle-1": 1
          },
          "strings": {
            "interpolation": "default"
          },
          "inTangent": 0,
          "inWeight": 0,
          "outTangent": 0,
          "outWeight": 0,
          "weightedMode": 0
        },
        {
          "property": "Left Hand Configuration",
          "index": 3,
          "time": 6.17676783,
          "ints": {
            "hash": -937919488
          },
          "floats": {
            "duration": 0
          },
          "strings": {
            "name": "-"
          },
          "inTangent": 0,
          "inWeight": 0,
          "outTangent": 0,
          "outWeight": 0,
          "weightedMode": 0
        },
        {
          "property": "Left Hand Configuration",
          "index": 2,
          "time": 5.66666746,
          "ints": {
            "hash": -1509998592
          },
          "floats": {
            "duration": 0
          },
          "strings": {
            "name": "-"
          },
          "inTangent": 0,
          "inWeight": 0,
          "outTangent": 0,
          "outWeight": 0,
          "weightedMode": 0
        },
        {
          "property": "Left Hand Configuration",
          "index": 1,
          "time": 5.11616135,
          "ints": {
            "hash": 1350396928
          },
          "floats": {
            "duration": 0
          },
          "strings": {
            "name": "-"
          },
          "inTangent": 0,
          "inWeight": 0,
          "outTangent": 0,
          "outWeight": 0,
          "weightedMode": 0
        },
        {
          "property": "Left Hand Configuration",
          "index": 5,
          "time": 1.01515138,
          "ints": {
            "hash": 569008128
          },
          "floats": {
            "duration": 0
          },
          "strings": {
            "name": "-"
          },
          "inTangent": 0,
          "inWeight": 0,
          "outTangent": 0,
          "outWeight": 0,
          "weightedMode": 0
        },
        {
          "property": "Left Hand Configuration",
          "index": 6,
          "time": 1.74242413,
          "ints": {
            "hash": 1713166336
          },
          "floats": {
            "duration": 0
          },
          "strings": {
            "name": "-"
          },
          "inTangent": 0,
          "inWeight": 0,
          "outTangent": 0,
          "outWeight": 0,
          "weightedMode": 0
        },
        {
          "property": "Left Hand Configuration",
          "index": 7,
          "time": 2.53535318,
          "ints": {
            "hash": -656253952
          },
          "floats": {
            "duration": 0
          },
          "strings": {
            "name": "-"
          },
          "inTangent": 0,
          "inWeight": 0,
          "outTangent": 0,
          "outWeight": 0,
          "weightedMode": 0
        },
        {
          "property": "Left Hand Configuration",
          "index": 8,
          "time": 3.25252581,
          "ints": {
            "hash": -946667520
          },
          "floats": {
            "duration": 0
          },
          "strings": {
            "name": "-"
          },
          "inTangent": 0,
          "inWeight": 0,
          "outTangent": 0,
          "outWeight": 0,
          "weightedMode": 0
        },
        {
          "property": "Left Hand Configuration",
          "index": 9,
          "time": 3.92424297,
          "ints": {
            "hash": 206238720
          },
          "floats": {
            "duration": 0
          },
          "strings": {
            "name": "-"
          },
          "inTangent": 0,
          "inWeight": 0,
          "outTangent": 0,
          "outWeight": 0,
          "weightedMode": 0
        },
        {
          "property": "Right Hand Configuration",
          "index": 3,
          "time": 6.17676783,
          "ints": {
            "hash": -1509998592
          },
          "floats": {
            "duration": 0
          },
          "strings": {
            "name": "3e3Fa"
          },
          "inTangent": 0,
          "inWeight": 0,
          "outTangent": 0,
          "outWeight": 0,
          "weightedMode": 0
        },
        {
          "property": "Right Hand Configuration",
          "index": 2,
          "time": 5.66666746,
          "ints": {
            "hash": -2082077696
          },
          "floats": {
            "duration": 0
          },
          "strings": {
            "name": "3e3Fa"
          },
          "inTangent": 0,
          "inWeight": 0,
          "outTangent": 0,
          "outWeight": 0,
          "weightedMode": 0
        },
        {
          "property": "Right Hand Configuration",
          "index": 1,
          "time": 5.11616135,
          "ints": {
            "hash": 778317824
          },
          "floats": {
            "duration": 0
          },
          "strings": {
            "name": "3e3Fa"
          },
          "inTangent": 0,
          "inWeight": 0,
          "outTangent": 0,
          "outWeight": 0,
          "weightedMode": 0
        },
        {
          "property": "Right Hand Configuration",
          "index": 5,
          "time": 1.01515138,
          "ints": {
            "hash": -3070976
          },
          "floats": {
            "duration": 0
          },
          "strings": {
            "name": "4eEa"
          },
          "inTangent": 0,
          "inWeight": 0,
          "outTangent": 0,
          "outWeight": 0,
          "weightedMode": 0
        },
        {
          "property": "Right Hand Configuration",
          "index": 6,
          "time": 1.74242413,
          "ints": {
            "hash": 1141087232
          },
          "floats": {
            "duration": 0
          },
          "strings": {
            "name": "4eEa"
          },
          "inTangent": 0,
          "inWeight": 0,
          "outTangent": 0,
          "outWeight": 0,
          "weightedMode": 0
        },
        {
          "property": "Right Hand Configuration",
          "index": 7,
          "time": 2.53535318,
          "ints": {
            "hash": -1228333056
          },
          "floats": {
            "duration": 0
          },
          "strings": {
            "name": "4eEa"
          },
          "inTangent": 0,
          "inWeight": 0,
          "outTangent": 0,
          "outWeight": 0,
          "weightedMode": 0
        },
        {
          "property": "Right Hand Configuration",
          "index": 8,
          "time": 3.25252581,
          "ints": {
            "hash": -2090825728
          },
          "floats": {
            "duration": 0
          },
          "strings": {
            "name": "4eEa"
          },
          "inTangent": 0,
          "inWeight": 0,
          "outTangent": 0,
          "outWeight": 0,
          "weightedMode": 0
        },
        {
          "property": "Right Hand Configuration",
          "index": 9,
          "time": 3.92424297,
          "ints": {
            "hash": -937919488
          },
          "floats": {
            "duration": 0
          },
          "strings": {
            "name": "4eEa"
          },
          "inTangent": 0,
          "inWeight": 0,
          "outTangent": 0,
          "outWeight": 0,
          "weightedMode": 0
        },
        {
          "property": "Facial Expression",
          "index": 3,
          "time": 6.17676783,
          "ints": {},
          "floats": {
            "duration": 0
          },
          "strings": {
            "faceName": "Neutra"
          },
          "inTangent": 0,
          "inWeight": 0,
          "outTangent": 0,
          "outWeight": 0,
          "weightedMode": 0
        },
        {
          "property": "Facial Expression",
          "index": 2,
          "time": 5.66666746,
          "ints": {},
          "floats": {
            "duration": 0
          },
          "strings": {
            "faceName": "Neutra"
          },
          "inTangent": 0,
          "inWeight": 0,
          "outTangent": 0,
          "outWeight": 0,
          "weightedMode": 0
        },
        {
          "property": "Facial Expression",
          "index": 1,
          "time": 5.11616135,
          "ints": {},
          "floats": {
            "duration": 0
          },
          "strings": {
            "faceName": "Neutra"
          },
          "inTangent": 0,
          "inWeight": 0,
          "outTangent": 0,
          "outWeight": 0,
          "weightedMode": 0
        },
        {
          "property": "Facial Expression",
          "index": 5,
          "time": 1.01515138,
          "ints": {},
          "floats": {
            "duration": 0
          },
          "strings": {
            "faceName": "Neutra"
          },
          "inTangent": 0,
          "inWeight": 0,
          "outTangent": 0,
          "outWeight": 0,
          "weightedMode": 0
        },
        {
          "property": "Facial Expression",
          "index": 6,
          "time": 1.74242413,
          "ints": {},
          "floats": {
            "duration": 0
          },
          "strings": {
            "faceName": "Neutra"
          },
          "inTangent": 0,
          "inWeight": 0,
          "outTangent": 0,
          "outWeight": 0,
          "weightedMode": 0
        },
        {
          "property": "Facial Expression",
          "index": 7,
          "time": 2.53535318,
          "ints": {},
          "floats": {
            "duration": 0
          },
          "strings": {
            "faceName": "Neutra"
          },
          "inTangent": 0,
          "inWeight": 0,
          "outTangent": 0,
          "outWeight": 0,
          "weightedMode": 0
        },
        {
          "property": "Facial Expression",
          "index": 8,
          "time": 3.25252581,
          "ints": {},
          "floats": {
            "duration": 0
          },
          "strings": {
            "faceName": "Neutra"
          },
          "inTangent": 0,
          "inWeight": 0,
          "outTangent": 0,
          "outWeight": 0,
          "weightedMode": 0
        },
        {
          "property": "Facial Expression",
          "index": 9,
          "time": 3.92424297,
          "ints": {},
          "floats": {
            "duration": 0
          },
          "strings": {
            "faceName": "Neutra"
          },
          "inTangent": 0,
          "inWeight": 0,
          "outTangent": 0,
          "outWeight": 0,
          "weightedMode": 0
        }
      ]
    },
    {
      "properties": [
        "Face Animation Neutra"
      ],
      "loops": false,
      "keyFrames": [
        {
          "property": "Face Animation Neutra",
          "index": 0,
          "time": 0,
          "ints": {},
          "floats": {
            "girl_head_.blendShape.mClose": 100,
            "girl_head_.blendShape.A": 0,
            "girl_head_.blendShape.Cons": 0,
            "girl_head_.blendShape.Fv": 0,
            "girl_head_.blendShape.mLSide": 0,
            "girl_head_.blendShape.mLSideUp": 0,
            "girl_head_.blendShape.mRSide": 0,
            "girl_head_.blendShape.mRSideUp": 0,
            "girl_head_.blendShape.O": 0,
            "girl_head_.blendShape.smile": 0,
            "girl_head_.blendShape.U": 0,
            "girl_hair.blendShape.cheek1": 0,
            "girl_hair.blendShape.cheek2": 0,
            "girl_hair.blendShape.cheek3": 0,
            "girl_head_.blendShape.Bmp": 0,
            "girl_head_.blendShape.E": 0,
            "girl_head_.blendShape.F001": 0,
            "girl_head_.blendShape.F003": 0,
            "girl_head_.blendShape.F005": 0,
            "girl_head_.blendShape.F006": 0,
            "girl_head_.blendShape.F007": 0,
            "girl_head_.blendShape.F007left": 0,
            "girl_head_.blendShape.F008": 0,
            "girl_head_.blendShape.F017": 0,
            "girl_head_.blendShape.F019": 0,
            "girl_head_.blendShape.F024": 0,
            "girl_head_.blendShape.F031": 0,
            "girl_head_.blendShape.LEyeBMad": 0,
            "girl_head_.blendShape.LEyeClose": 0,
            "girl_head_.blendShape.LEyeLidUp": 0,
            "girl_head_.blendShape.LEyeMad": 0,
            "girl_head_.blendShape.LEyeSad": 0,
            "girl_head_.blendShape.LeyeBUp": 0,
            "girl_head_.blendShape.mSad": 0,
            "girl_head_.blendShape.REyeBMad": 0,
            "girl_head_.blendShape.REyeClose": 0,
            "girl_head_.blendShape.REyeLidUp": 0,
            "girl_head_.blendShape.REyeMad": 0,
            "girl_head_.blendShape.REyeSad": 0,
            "girl_head_.blendShape.ReyeBSad": 0,
            "girl_head_.blendShape.ReyeBUp": 0,
            "girl_head_.blendShape.ReyeLSad": 0,
            "tgrl1_dmyHeadObjsRoot/tgrl1_logGumTeethAngle/tgrl1_logGumTeethMove/tgrl1_tongue.blendShape.tongue_A": 0,
            "tgrl1_dmyHeadObjsRoot/tgrl1_logGumTeethAngle/tgrl1_logGumTeethMove/tgrl1_tongue.blendShape.tongue_down": 0,
            "tgrl1_dmyHeadObjsRoot/tgrl1_logGumTeethAngle/tgrl1_logGumTeethMove/tgrl1_tongue.blendShape.tongue_F007": 0,
            "tgrl1_dmyHeadObjsRoot/tgrl1_logGumTeethAngle/tgrl1_logGumTeethMove/tgrl1_tongue.blendShape.tongue_F007left": 0,
            "tgrl1_dmyHeadObjsRoot/tgrl1_logGumTeethAngle/tgrl1_logGumTeethMove/tgrl1_tongue.blendShape.tongue_left": 0,
            "tgrl1_dmyHeadObjsRoot/tgrl1_logGumTeethAngle/tgrl1_logGumTeethMove/tgrl1_tongue.blendShape.tongue_O": 0,
            "tgrl1_dmyHeadObjsRoot/tgrl1_logGumTeethAngle/tgrl1_logGumTeethMove/tgrl1_tongue.blendShape.tongue_out": 0,
            "tgrl1_dmyHeadObjsRoot/tgrl1_logGumTeethAngle/tgrl1_logGumTeethMove/tgrl1_tongue.blendShape.tongue_right": 0,
            "tgrl1_dmyHeadObjsRoot/tgrl1_logGumTeethAngle/tgrl1_logGumTeethMove/tgrl1_tongue.blendShape.tongue_up": 0,
            "rig_CharRoot/bip/bip Pelvis/bip Spine/bip Spine1/bip Neck/bip Head/rig_boneTongue.m_LocalPosition.x": -0.0188717656,
            "rig_CharRoot/bip/bip Pelvis/bip Spine/bip Spine1/bip Neck/bip Head/rig_boneTongue.m_LocalPosition.y": 0.0733392909,
            "rig_CharRoot/bip/bip Pelvis/bip Spine/bip Spine1/bip Neck/bip Head/rig_boneTongue.m_LocalPosition.z": 1.52587887E-07,
            "rig_CharRoot/bip/bip Pelvis/bip Spine/bip Spine1/bip Neck/bip Head/rig_boneTongue.localEulerAnglesRaw.x": 178.884003,
            "rig_CharRoot/bip/bip Pelvis/bip Spine/bip Spine1/bip Neck/bip Head/rig_boneTongue.localEulerAnglesRaw.y": 89.9999924,
            "rig_CharRoot/bip/bip Pelvis/bip Spine/bip Spine1/bip Neck/bip Head/rig_boneTongue.localEulerAnglesRaw.z": 0,
            "rig_CharRoot/bip/bip Pelvis/bip Spine/bip Spine1/bip Neck/bip Head/rig_boneTongue.m_LocalScale.x": 1,
            "rig_CharRoot/bip/bip Pelvis/bip Spine/bip Spine1/bip Neck/bip Head/rig_boneTongue.m_LocalScale.y": 1,
            "rig_CharRoot/bip/bip Pelvis/bip Spine/bip Spine1/bip Neck/bip Head/rig_boneTongue.m_LocalScale.z": 1,
            "muscle15": 0,
            "muscle17": 0
          },
          "strings": {},
          "inTangent": 0,
          "inWeight": 0.333333343,
          "outTangent": 0,
          "outWeight": 0.333333343,
          "weightedMode": 0
        }
      ]
    },
    {
      "properties": [
        "Face Animation Neutra"
      ],
      "loops": false,
      "keyFrames": [
        {
          "property": "Face Animation Neutra",
          "index": 0,
          "time": 0,
          "ints": {},
          "floats": {
            "girl_head_.blendShape.mClose": 100,
            "girl_head_.blendShape.A": 0,
            "girl_head_.blendShape.Cons": 0,
            "girl_head_.blendShape.Fv": 0,
            "girl_head_.blendShape.mLSide": 0,
            "girl_head_.blendShape.mLSideUp": 0,
            "girl_head_.blendShape.mRSide": 0,
            "girl_head_.blendShape.mRSideUp": 0,
            "girl_head_.blendShape.O": 0,
            "girl_head_.blendShape.smile": 0,
            "girl_head_.blendShape.U": 0,
            "girl_hair.blendShape.cheek1": 0,
            "girl_hair.blendShape.cheek2": 0,
            "girl_hair.blendShape.cheek3": 0,
            "girl_head_.blendShape.Bmp": 0,
            "girl_head_.blendShape.E": 0,
            "girl_head_.blendShape.F001": 0,
            "girl_head_.blendShape.F003": 0,
            "girl_head_.blendShape.F005": 0,
            "girl_head_.blendShape.F006": 0,
            "girl_head_.blendShape.F007": 0,
            "girl_head_.blendShape.F007left": 0,
            "girl_head_.blendShape.F008": 0,
            "girl_head_.blendShape.F017": 0,
            "girl_head_.blendShape.F019": 0,
            "girl_head_.blendShape.F024": 0,
            "girl_head_.blendShape.F031": 0,
            "girl_head_.blendShape.LEyeBMad": 0,
            "girl_head_.blendShape.LEyeClose": 0,
            "girl_head_.blendShape.LEyeLidUp": 0,
            "girl_head_.blendShape.LEyeMad": 0,
            "girl_head_.blendShape.LEyeSad": 0,
            "girl_head_.blendShape.LeyeBUp": 0,
            "girl_head_.blendShape.mSad": 0,
            "girl_head_.blendShape.REyeBMad": 0,
            "girl_head_.blendShape.REyeClose": 0,
            "girl_head_.blendShape.REyeLidUp": 0,
            "girl_head_.blendShape.REyeMad": 0,
            "girl_head_.blendShape.REyeSad": 0,
            "girl_head_.blendShape.ReyeBSad": 0,
            "girl_head_.blendShape.ReyeBUp": 0,
            "girl_head_.blendShape.ReyeLSad": 0,
            "tgrl1_dmyHeadObjsRoot/tgrl1_logGumTeethAngle/tgrl1_logGumTeethMove/tgrl1_tongue.blendShape.tongue_A": 0,
            "tgrl1_dmyHeadObjsRoot/tgrl1_logGumTeethAngle/tgrl1_logGumTeethMove/tgrl1_tongue.blendShape.tongue_down": 0,
            "tgrl1_dmyHeadObjsRoot/tgrl1_logGumTeethAngle/tgrl1_logGumTeethMove/tgrl1_tongue.blendShape.tongue_F007": 0,
            "tgrl1_dmyHeadObjsRoot/tgrl1_logGumTeethAngle/tgrl1_logGumTeethMove/tgrl1_tongue.blendShape.tongue_F007left": 0,
            "tgrl1_dmyHeadObjsRoot/tgrl1_logGumTeethAngle/tgrl1_logGumTeethMove/tgrl1_tongue.blendShape.tongue_left": 0,
            "tgrl1_dmyHeadObjsRoot/tgrl1_logGumTeethAngle/tgrl1_logGumTeethMove/tgrl1_tongue.blendShape.tongue_O": 0,
            "tgrl1_dmyHeadObjsRoot/tgrl1_logGumTeethAngle/tgrl1_logGumTeethMove/tgrl1_tongue.blendShape.tongue_out": 0,
            "tgrl1_dmyHeadObjsRoot/tgrl1_logGumTeethAngle/tgrl1_logGumTeethMove/tgrl1_tongue.blendShape.tongue_right": 0,
            "tgrl1_dmyHeadObjsRoot/tgrl1_logGumTeethAngle/tgrl1_logGumTeethMove/tgrl1_tongue.blendShape.tongue_up": 0,
            "rig_CharRoot/bip/bip Pelvis/bip Spine/bip Spine1/bip Neck/bip Head/rig_boneTongue.m_LocalPosition.x": -0.0188717656,
            "rig_CharRoot/bip/bip Pelvis/bip Spine/bip Spine1/bip Neck/bip Head/rig_boneTongue.m_LocalPosition.y": 0.0733392909,
            "rig_CharRoot/bip/bip Pelvis/bip Spine/bip Spine1/bip Neck/bip Head/rig_boneTongue.m_LocalPosition.z": 1.52587887E-07,
            "rig_CharRoot/bip/bip Pelvis/bip Spine/bip Spine1/bip Neck/bip Head/rig_boneTongue.localEulerAnglesRaw.x": 178.884003,
            "rig_CharRoot/bip/bip Pelvis/bip Spine/bip Spine1/bip Neck/bip Head/rig_boneTongue.localEulerAnglesRaw.y": 89.9999924,
            "rig_CharRoot/bip/bip Pelvis/bip Spine/bip Spine1/bip Neck/bip Head/rig_boneTongue.localEulerAnglesRaw.z": 0,
            "rig_CharRoot/bip/bip Pelvis/bip Spine/bip Spine1/bip Neck/bip Head/rig_boneTongue.m_LocalScale.x": 1,
            "rig_CharRoot/bip/bip Pelvis/bip Spine/bip Spine1/bip Neck/bip Head/rig_boneTongue.m_LocalScale.y": 1,
            "rig_CharRoot/bip/bip Pelvis/bip Spine/bip Spine1/bip Neck/bip Head/rig_boneTongue.m_LocalScale.z": 1,
            "muscle15": 0,
            "muscle17": 0
          },
          "strings": {},
          "inTangent": 0,
          "inWeight": 0.333333343,
          "outTangent": 0,
          "outWeight": 0.333333343,
          "weightedMode": 0
        }
      ]
    },
    {
      "properties": [
        "Face Animation Neutra"
      ],
      "loops": false,
      "keyFrames": [
        {
          "property": "Face Animation Neutra",
          "index": 0,
          "time": 0,
          "ints": {},
          "floats": {
            "girl_head_.blendShape.mClose": 100,
            "girl_head_.blendShape.A": 0,
            "girl_head_.blendShape.Cons": 0,
            "girl_head_.blendShape.Fv": 0,
            "girl_head_.blendShape.mLSide": 0,
            "girl_head_.blendShape.mLSideUp": 0,
            "girl_head_.blendShape.mRSide": 0,
            "girl_head_.blendShape.mRSideUp": 0,
            "girl_head_.blendShape.O": 0,
            "girl_head_.blendShape.smile": 0,
            "girl_head_.blendShape.U": 0,
            "girl_hair.blendShape.cheek1": 0,
            "girl_hair.blendShape.cheek2": 0,
            "girl_hair.blendShape.cheek3": 0,
            "girl_head_.blendShape.Bmp": 0,
            "girl_head_.blendShape.E": 0,
            "girl_head_.blendShape.F001": 0,
            "girl_head_.blendShape.F003": 0,
            "girl_head_.blendShape.F005": 0,
            "girl_head_.blendShape.F006": 0,
            "girl_head_.blendShape.F007": 0,
            "girl_head_.blendShape.F007left": 0,
            "girl_head_.blendShape.F008": 0,
            "girl_head_.blendShape.F017": 0,
            "girl_head_.blendShape.F019": 0,
            "girl_head_.blendShape.F024": 0,
            "girl_head_.blendShape.F031": 0,
            "girl_head_.blendShape.LEyeBMad": 0,
            "girl_head_.blendShape.LEyeClose": 0,
            "girl_head_.blendShape.LEyeLidUp": 0,
            "girl_head_.blendShape.LEyeMad": 0,
            "girl_head_.blendShape.LEyeSad": 0,
            "girl_head_.blendShape.LeyeBUp": 0,
            "girl_head_.blendShape.mSad": 0,
            "girl_head_.blendShape.REyeBMad": 0,
            "girl_head_.blendShape.REyeClose": 0,
            "girl_head_.blendShape.REyeLidUp": 0,
            "girl_head_.blendShape.REyeMad": 0,
            "girl_head_.blendShape.REyeSad": 0,
            "girl_head_.blendShape.ReyeBSad": 0,
            "girl_head_.blendShape.ReyeBUp": 0,
            "girl_head_.blendShape.ReyeLSad": 0,
            "tgrl1_dmyHeadObjsRoot/tgrl1_logGumTeethAngle/tgrl1_logGumTeethMove/tgrl1_tongue.blendShape.tongue_A": 0,
            "tgrl1_dmyHeadObjsRoot/tgrl1_logGumTeethAngle/tgrl1_logGumTeethMove/tgrl1_tongue.blendShape.tongue_down": 0,
            "tgrl1_dmyHeadObjsRoot/tgrl1_logGumTeethAngle/tgrl1_logGumTeethMove/tgrl1_tongue.blendShape.tongue_F007": 0,
            "tgrl1_dmyHeadObjsRoot/tgrl1_logGumTeethAngle/tgrl1_logGumTeethMove/tgrl1_tongue.blendShape.tongue_F007left": 0,
            "tgrl1_dmyHeadObjsRoot/tgrl1_logGumTeethAngle/tgrl1_logGumTeethMove/tgrl1_tongue.blendShape.tongue_left": 0,
            "tgrl1_dmyHeadObjsRoot/tgrl1_logGumTeethAngle/tgrl1_logGumTeethMove/tgrl1_tongue.blendShape.tongue_O": 0,
            "tgrl1_dmyHeadObjsRoot/tgrl1_logGumTeethAngle/tgrl1_logGumTeethMove/tgrl1_tongue.blendShape.tongue_out": 0,
            "tgrl1_dmyHeadObjsRoot/tgrl1_logGumTeethAngle/tgrl1_logGumTeethMove/tgrl1_tongue.blendShape.tongue_right": 0,
            "tgrl1_dmyHeadObjsRoot/tgrl1_logGumTeethAngle/tgrl1_logGumTeethMove/tgrl1_tongue.blendShape.tongue_up": 0,
            "rig_CharRoot/bip/bip Pelvis/bip Spine/bip Spine1/bip Neck/bip Head/rig_boneTongue.m_LocalPosition.x": -0.0188717656,
            "rig_CharRoot/bip/bip Pelvis/bip Spine/bip Spine1/bip Neck/bip Head/rig_boneTongue.m_LocalPosition.y": 0.0733392909,
            "rig_CharRoot/bip/bip Pelvis/bip Spine/bip Spine1/bip Neck/bip Head/rig_boneTongue.m_LocalPosition.z": 1.52587887E-07,
            "rig_CharRoot/bip/bip Pelvis/bip Spine/bip Spine1/bip Neck/bip Head/rig_boneTongue.localEulerAnglesRaw.x": 178.884003,
            "rig_CharRoot/bip/bip Pelvis/bip Spine/bip Spine1/bip Neck/bip Head/rig_boneTongue.localEulerAnglesRaw.y": 89.9999924,
            "rig_CharRoot/bip/bip Pelvis/bip Spine/bip Spine1/bip Neck/bip Head/rig_boneTongue.localEulerAnglesRaw.z": 0,
            "rig_CharRoot/bip/bip Pelvis/bip Spine/bip Spine1/bip Neck/bip Head/rig_boneTongue.m_LocalScale.x": 1,
            "rig_CharRoot/bip/bip Pelvis/bip Spine/bip Spine1/bip Neck/bip Head/rig_boneTongue.m_LocalScale.y": 1,
            "rig_CharRoot/bip/bip Pelvis/bip Spine/bip Spine1/bip Neck/bip Head/rig_boneTongue.m_LocalScale.z": 1,
            "muscle15": 0,
            "muscle17": 0
          },
          "strings": {},
          "inTangent": 0,
          "inWeight": 0.333333343,
          "outTangent": 0,
          "outWeight": 0.333333343,
          "weightedMode": 0
        }
      ]
    },
    {
      "properties": [
        "Face Animation Neutra"
      ],
      "loops": false,
      "keyFrames": [
        {
          "property": "Face Animation Neutra",
          "index": 0,
          "time": 0,
          "ints": {},
          "floats": {
            "girl_head_.blendShape.mClose": 100,
            "girl_head_.blendShape.A": 0,
            "girl_head_.blendShape.Cons": 0,
            "girl_head_.blendShape.Fv": 0,
            "girl_head_.blendShape.mLSide": 0,
            "girl_head_.blendShape.mLSideUp": 0,
            "girl_head_.blendShape.mRSide": 0,
            "girl_head_.blendShape.mRSideUp": 0,
            "girl_head_.blendShape.O": 0,
            "girl_head_.blendShape.smile": 0,
            "girl_head_.blendShape.U": 0,
            "girl_hair.blendShape.cheek1": 0,
            "girl_hair.blendShape.cheek2": 0,
            "girl_hair.blendShape.cheek3": 0,
            "girl_head_.blendShape.Bmp": 0,
            "girl_head_.blendShape.E": 0,
            "girl_head_.blendShape.F001": 0,
            "girl_head_.blendShape.F003": 0,
            "girl_head_.blendShape.F005": 0,
            "girl_head_.blendShape.F006": 0,
            "girl_head_.blendShape.F007": 0,
            "girl_head_.blendShape.F007left": 0,
            "girl_head_.blendShape.F008": 0,
            "girl_head_.blendShape.F017": 0,
            "girl_head_.blendShape.F019": 0,
            "girl_head_.blendShape.F024": 0,
            "girl_head_.blendShape.F031": 0,
            "girl_head_.blendShape.LEyeBMad": 0,
            "girl_head_.blendShape.LEyeClose": 0,
            "girl_head_.blendShape.LEyeLidUp": 0,
            "girl_head_.blendShape.LEyeMad": 0,
            "girl_head_.blendShape.LEyeSad": 0,
            "girl_head_.blendShape.LeyeBUp": 0,
            "girl_head_.blendShape.mSad": 0,
            "girl_head_.blendShape.REyeBMad": 0,
            "girl_head_.blendShape.REyeClose": 0,
            "girl_head_.blendShape.REyeLidUp": 0,
            "girl_head_.blendShape.REyeMad": 0,
            "girl_head_.blendShape.REyeSad": 0,
            "girl_head_.blendShape.ReyeBSad": 0,
            "girl_head_.blendShape.ReyeBUp": 0,
            "girl_head_.blendShape.ReyeLSad": 0,
            "tgrl1_dmyHeadObjsRoot/tgrl1_logGumTeethAngle/tgrl1_logGumTeethMove/tgrl1_tongue.blendShape.tongue_A": 0,
            "tgrl1_dmyHeadObjsRoot/tgrl1_logGumTeethAngle/tgrl1_logGumTeethMove/tgrl1_tongue.blendShape.tongue_down": 0,
            "tgrl1_dmyHeadObjsRoot/tgrl1_logGumTeethAngle/tgrl1_logGumTeethMove/tgrl1_tongue.blendShape.tongue_F007": 0,
            "tgrl1_dmyHeadObjsRoot/tgrl1_logGumTeethAngle/tgrl1_logGumTeethMove/tgrl1_tongue.blendShape.tongue_F007left": 0,
            "tgrl1_dmyHeadObjsRoot/tgrl1_logGumTeethAngle/tgrl1_logGumTeethMove/tgrl1_tongue.blendShape.tongue_left": 0,
            "tgrl1_dmyHeadObjsRoot/tgrl1_logGumTeethAngle/tgrl1_logGumTeethMove/tgrl1_tongue.blendShape.tongue_O": 0,
            "tgrl1_dmyHeadObjsRoot/tgrl1_logGumTeethAngle/tgrl1_logGumTeethMove/tgrl1_tongue.blendShape.tongue_out": 0,
            "tgrl1_dmyHeadObjsRoot/tgrl1_logGumTeethAngle/tgrl1_logGumTeethMove/tgrl1_tongue.blendShape.tongue_right": 0,
            "tgrl1_dmyHeadObjsRoot/tgrl1_logGumTeethAngle/tgrl1_logGumTeethMove/tgrl1_tongue.blendShape.tongue_up": 0,
            "rig_CharRoot/bip/bip Pelvis/bip Spine/bip Spine1/bip Neck/bip Head/rig_boneTongue.m_LocalPosition.x": -0.0188717656,
            "rig_CharRoot/bip/bip Pelvis/bip Spine/bip Spine1/bip Neck/bip Head/rig_boneTongue.m_LocalPosition.y": 0.0733392909,
            "rig_CharRoot/bip/bip Pelvis/bip Spine/bip Spine1/bip Neck/bip Head/rig_boneTongue.m_LocalPosition.z": 1.52587887E-07,
            "rig_CharRoot/bip/bip Pelvis/bip Spine/bip Spine1/bip Neck/bip Head/rig_boneTongue.localEulerAnglesRaw.x": 178.884003,
            "rig_CharRoot/bip/bip Pelvis/bip Spine/bip Spine1/bip Neck/bip Head/rig_boneTongue.localEulerAnglesRaw.y": 89.9999924,
            "rig_CharRoot/bip/bip Pelvis/bip Spine/bip Spine1/bip Neck/bip Head/rig_boneTongue.localEulerAnglesRaw.z": 0,
            "rig_CharRoot/bip/bip Pelvis/bip Spine/bip Spine1/bip Neck/bip Head/rig_boneTongue.m_LocalScale.x": 1,
            "rig_CharRoot/bip/bip Pelvis/bip Spine/bip Spine1/bip Neck/bip Head/rig_boneTongue.m_LocalScale.y": 1,
            "rig_CharRoot/bip/bip Pelvis/bip Spine/bip Spine1/bip Neck/bip Head/rig_boneTongue.m_LocalScale.z": 1,
            "muscle15": 0,
            "muscle17": 0
          },
          "strings": {},
          "inTangent": 0,
          "inWeight": 0.333333343,
          "outTangent": 0,
          "outWeight": 0.333333343,
          "weightedMode": 0
        }
      ]
    },
    {
      "properties": [
        "Face Animation Neutra"
      ],
      "loops": false,
      "keyFrames": [
        {
          "property": "Face Animation Neutra",
          "index": 0,
          "time": 0,
          "ints": {},
          "floats": {
            "girl_head_.blendShape.mClose": 100,
            "girl_head_.blendShape.A": 0,
            "girl_head_.blendShape.Cons": 0,
            "girl_head_.blendShape.Fv": 0,
            "girl_head_.blendShape.mLSide": 0,
            "girl_head_.blendShape.mLSideUp": 0,
            "girl_head_.blendShape.mRSide": 0,
            "girl_head_.blendShape.mRSideUp": 0,
            "girl_head_.blendShape.O": 0,
            "girl_head_.blendShape.smile": 0,
            "girl_head_.blendShape.U": 0,
            "girl_hair.blendShape.cheek1": 0,
            "girl_hair.blendShape.cheek2": 0,
            "girl_hair.blendShape.cheek3": 0,
            "girl_head_.blendShape.Bmp": 0,
            "girl_head_.blendShape.E": 0,
            "girl_head_.blendShape.F001": 0,
            "girl_head_.blendShape.F003": 0,
            "girl_head_.blendShape.F005": 0,
            "girl_head_.blendShape.F006": 0,
            "girl_head_.blendShape.F007": 0,
            "girl_head_.blendShape.F007left": 0,
            "girl_head_.blendShape.F008": 0,
            "girl_head_.blendShape.F017": 0,
            "girl_head_.blendShape.F019": 0,
            "girl_head_.blendShape.F024": 0,
            "girl_head_.blendShape.F031": 0,
            "girl_head_.blendShape.LEyeBMad": 0,
            "girl_head_.blendShape.LEyeClose": 0,
            "girl_head_.blendShape.LEyeLidUp": 0,
            "girl_head_.blendShape.LEyeMad": 0,
            "girl_head_.blendShape.LEyeSad": 0,
            "girl_head_.blendShape.LeyeBUp": 0,
            "girl_head_.blendShape.mSad": 0,
            "girl_head_.blendShape.REyeBMad": 0,
            "girl_head_.blendShape.REyeClose": 0,
            "girl_head_.blendShape.REyeLidUp": 0,
            "girl_head_.blendShape.REyeMad": 0,
            "girl_head_.blendShape.REyeSad": 0,
            "girl_head_.blendShape.ReyeBSad": 0,
            "girl_head_.blendShape.ReyeBUp": 0,
            "girl_head_.blendShape.ReyeLSad": 0,
            "tgrl1_dmyHeadObjsRoot/tgrl1_logGumTeethAngle/tgrl1_logGumTeethMove/tgrl1_tongue.blendShape.tongue_A": 0,
            "tgrl1_dmyHeadObjsRoot/tgrl1_logGumTeethAngle/tgrl1_logGumTeethMove/tgrl1_tongue.blendShape.tongue_down": 0,
            "tgrl1_dmyHeadObjsRoot/tgrl1_logGumTeethAngle/tgrl1_logGumTeethMove/tgrl1_tongue.blendShape.tongue_F007": 0,
            "tgrl1_dmyHeadObjsRoot/tgrl1_logGumTeethAngle/tgrl1_logGumTeethMove/tgrl1_tongue.blendShape.tongue_F007left": 0,
            "tgrl1_dmyHeadObjsRoot/tgrl1_logGumTeethAngle/tgrl1_logGumTeethMove/tgrl1_tongue.blendShape.tongue_left": 0,
            "tgrl1_dmyHeadObjsRoot/tgrl1_logGumTeethAngle/tgrl1_logGumTeethMove/tgrl1_tongue.blendShape.tongue_O": 0,
            "tgrl1_dmyHeadObjsRoot/tgrl1_logGumTeethAngle/tgrl1_logGumTeethMove/tgrl1_tongue.blendShape.tongue_out": 0,
            "tgrl1_dmyHeadObjsRoot/tgrl1_logGumTeethAngle/tgrl1_logGumTeethMove/tgrl1_tongue.blendShape.tongue_right": 0,
            "tgrl1_dmyHeadObjsRoot/tgrl1_logGumTeethAngle/tgrl1_logGumTeethMove/tgrl1_tongue.blendShape.tongue_up": 0,
            "rig_CharRoot/bip/bip Pelvis/bip Spine/bip Spine1/bip Neck/bip Head/rig_boneTongue.m_LocalPosition.x": -0.0188717656,
            "rig_CharRoot/bip/bip Pelvis/bip Spine/bip Spine1/bip Neck/bip Head/rig_boneTongue.m_LocalPosition.y": 0.0733392909,
            "rig_CharRoot/bip/bip Pelvis/bip Spine/bip Spine1/bip Neck/bip Head/rig_boneTongue.m_LocalPosition.z": 1.52587887E-07,
            "rig_CharRoot/bip/bip Pelvis/bip Spine/bip Spine1/bip Neck/bip Head/rig_boneTongue.localEulerAnglesRaw.x": 178.884003,
            "rig_CharRoot/bip/bip Pelvis/bip Spine/bip Spine1/bip Neck/bip Head/rig_boneTongue.localEulerAnglesRaw.y": 89.9999924,
            "rig_CharRoot/bip/bip Pelvis/bip Spine/bip Spine1/bip Neck/bip Head/rig_boneTongue.localEulerAnglesRaw.z": 0,
            "rig_CharRoot/bip/bip Pelvis/bip Spine/bip Spine1/bip Neck/bip Head/rig_boneTongue.m_LocalScale.x": 1,
            "rig_CharRoot/bip/bip Pelvis/bip Spine/bip Spine1/bip Neck/bip Head/rig_boneTongue.m_LocalScale.y": 1,
            "rig_CharRoot/bip/bip Pelvis/bip Spine/bip Spine1/bip Neck/bip Head/rig_boneTongue.m_LocalScale.z": 1,
            "muscle15": 0,
            "muscle17": 0
          },
          "strings": {},
          "inTangent": 0,
          "inWeight": 0.333333343,
          "outTangent": 0,
          "outWeight": 0.333333343,
          "weightedMode": 0
        }
      ]
    },
    {
      "properties": [
        "Face Animation Neutra"
      ],
      "loops": false,
      "keyFrames": [
        {
          "property": "Face Animation Neutra",
          "index": 0,
          "time": 0,
          "ints": {},
          "floats": {
            "girl_head_.blendShape.mClose": 100,
            "girl_head_.blendShape.A": 0,
            "girl_head_.blendShape.Cons": 0,
            "girl_head_.blendShape.Fv": 0,
            "girl_head_.blendShape.mLSide": 0,
            "girl_head_.blendShape.mLSideUp": 0,
            "girl_head_.blendShape.mRSide": 0,
            "girl_head_.blendShape.mRSideUp": 0,
            "girl_head_.blendShape.O": 0,
            "girl_head_.blendShape.smile": 0,
            "girl_head_.blendShape.U": 0,
            "girl_hair.blendShape.cheek1": 0,
            "girl_hair.blendShape.cheek2": 0,
            "girl_hair.blendShape.cheek3": 0,
            "girl_head_.blendShape.Bmp": 0,
            "girl_head_.blendShape.E": 0,
            "girl_head_.blendShape.F001": 0,
            "girl_head_.blendShape.F003": 0,
            "girl_head_.blendShape.F005": 0,
            "girl_head_.blendShape.F006": 0,
            "girl_head_.blendShape.F007": 0,
            "girl_head_.blendShape.F007left": 0,
            "girl_head_.blendShape.F008": 0,
            "girl_head_.blendShape.F017": 0,
            "girl_head_.blendShape.F019": 0,
            "girl_head_.blendShape.F024": 0,
            "girl_head_.blendShape.F031": 0,
            "girl_head_.blendShape.LEyeBMad": 0,
            "girl_head_.blendShape.LEyeClose": 0,
            "girl_head_.blendShape.LEyeLidUp": 0,
            "girl_head_.blendShape.LEyeMad": 0,
            "girl_head_.blendShape.LEyeSad": 0,
            "girl_head_.blendShape.LeyeBUp": 0,
            "girl_head_.blendShape.mSad": 0,
            "girl_head_.blendShape.REyeBMad": 0,
            "girl_head_.blendShape.REyeClose": 0,
            "girl_head_.blendShape.REyeLidUp": 0,
            "girl_head_.blendShape.REyeMad": 0,
            "girl_head_.blendShape.REyeSad": 0,
            "girl_head_.blendShape.ReyeBSad": 0,
            "girl_head_.blendShape.ReyeBUp": 0,
            "girl_head_.blendShape.ReyeLSad": 0,
            "tgrl1_dmyHeadObjsRoot/tgrl1_logGumTeethAngle/tgrl1_logGumTeethMove/tgrl1_tongue.blendShape.tongue_A": 0,
            "tgrl1_dmyHeadObjsRoot/tgrl1_logGumTeethAngle/tgrl1_logGumTeethMove/tgrl1_tongue.blendShape.tongue_down": 0,
            "tgrl1_dmyHeadObjsRoot/tgrl1_logGumTeethAngle/tgrl1_logGumTeethMove/tgrl1_tongue.blendShape.tongue_F007": 0,
            "tgrl1_dmyHeadObjsRoot/tgrl1_logGumTeethAngle/tgrl1_logGumTeethMove/tgrl1_tongue.blendShape.tongue_F007left": 0,
            "tgrl1_dmyHeadObjsRoot/tgrl1_logGumTeethAngle/tgrl1_logGumTeethMove/tgrl1_tongue.blendShape.tongue_left": 0,
            "tgrl1_dmyHeadObjsRoot/tgrl1_logGumTeethAngle/tgrl1_logGumTeethMove/tgrl1_tongue.blendShape.tongue_O": 0,
            "tgrl1_dmyHeadObjsRoot/tgrl1_logGumTeethAngle/tgrl1_logGumTeethMove/tgrl1_tongue.blendShape.tongue_out": 0,
            "tgrl1_dmyHeadObjsRoot/tgrl1_logGumTeethAngle/tgrl1_logGumTeethMove/tgrl1_tongue.blendShape.tongue_right": 0,
            "tgrl1_dmyHeadObjsRoot/tgrl1_logGumTeethAngle/tgrl1_logGumTeethMove/tgrl1_tongue.blendShape.tongue_up": 0,
            "rig_CharRoot/bip/bip Pelvis/bip Spine/bip Spine1/bip Neck/bip Head/rig_boneTongue.m_LocalPosition.x": -0.0188717656,
            "rig_CharRoot/bip/bip Pelvis/bip Spine/bip Spine1/bip Neck/bip Head/rig_boneTongue.m_LocalPosition.y": 0.0733392909,
            "rig_CharRoot/bip/bip Pelvis/bip Spine/bip Spine1/bip Neck/bip Head/rig_boneTongue.m_LocalPosition.z": 1.52587887E-07,
            "rig_CharRoot/bip/bip Pelvis/bip Spine/bip Spine1/bip Neck/bip Head/rig_boneTongue.localEulerAnglesRaw.x": 178.884003,
            "rig_CharRoot/bip/bip Pelvis/bip Spine/bip Spine1/bip Neck/bip Head/rig_boneTongue.localEulerAnglesRaw.y": 89.9999924,
            "rig_CharRoot/bip/bip Pelvis/bip Spine/bip Spine1/bip Neck/bip Head/rig_boneTongue.localEulerAnglesRaw.z": 0,
            "rig_CharRoot/bip/bip Pelvis/bip Spine/bip Spine1/bip Neck/bip Head/rig_boneTongue.m_LocalScale.x": 1,
            "rig_CharRoot/bip/bip Pelvis/bip Spine/bip Spine1/bip Neck/bip Head/rig_boneTongue.m_LocalScale.y": 1,
            "rig_CharRoot/bip/bip Pelvis/bip Spine/bip Spine1/bip Neck/bip Head/rig_boneTongue.m_LocalScale.z": 1,
            "muscle15": 0,
            "muscle17": 0
          },
          "strings": {},
          "inTangent": 0,
          "inWeight": 0.333333343,
          "outTangent": 0,
          "outWeight": 0.333333343,
          "weightedMode": 0
        }
      ]
    },
    {
      "properties": [
        "Face Animation Neutra"
      ],
      "loops": false,
      "keyFrames": [
        {
          "property": "Face Animation Neutra",
          "index": 0,
          "time": 0,
          "ints": {},
          "floats": {
            "girl_head_.blendShape.mClose": 100,
            "girl_head_.blendShape.A": 0,
            "girl_head_.blendShape.Cons": 0,
            "girl_head_.blendShape.Fv": 0,
            "girl_head_.blendShape.mLSide": 0,
            "girl_head_.blendShape.mLSideUp": 0,
            "girl_head_.blendShape.mRSide": 0,
            "girl_head_.blendShape.mRSideUp": 0,
            "girl_head_.blendShape.O": 0,
            "girl_head_.blendShape.smile": 0,
            "girl_head_.blendShape.U": 0,
            "girl_hair.blendShape.cheek1": 0,
            "girl_hair.blendShape.cheek2": 0,
            "girl_hair.blendShape.cheek3": 0,
            "girl_head_.blendShape.Bmp": 0,
            "girl_head_.blendShape.E": 0,
            "girl_head_.blendShape.F001": 0,
            "girl_head_.blendShape.F003": 0,
            "girl_head_.blendShape.F005": 0,
            "girl_head_.blendShape.F006": 0,
            "girl_head_.blendShape.F007": 0,
            "girl_head_.blendShape.F007left": 0,
            "girl_head_.blendShape.F008": 0,
            "girl_head_.blendShape.F017": 0,
            "girl_head_.blendShape.F019": 0,
            "girl_head_.blendShape.F024": 0,
            "girl_head_.blendShape.F031": 0,
            "girl_head_.blendShape.LEyeBMad": 0,
            "girl_head_.blendShape.LEyeClose": 0,
            "girl_head_.blendShape.LEyeLidUp": 0,
            "girl_head_.blendShape.LEyeMad": 0,
            "girl_head_.blendShape.LEyeSad": 0,
            "girl_head_.blendShape.LeyeBUp": 0,
            "girl_head_.blendShape.mSad": 0,
            "girl_head_.blendShape.REyeBMad": 0,
            "girl_head_.blendShape.REyeClose": 0,
            "girl_head_.blendShape.REyeLidUp": 0,
            "girl_head_.blendShape.REyeMad": 0,
            "girl_head_.blendShape.REyeSad": 0,
            "girl_head_.blendShape.ReyeBSad": 0,
            "girl_head_.blendShape.ReyeBUp": 0,
            "girl_head_.blendShape.ReyeLSad": 0,
            "tgrl1_dmyHeadObjsRoot/tgrl1_logGumTeethAngle/tgrl1_logGumTeethMove/tgrl1_tongue.blendShape.tongue_A": 0,
            "tgrl1_dmyHeadObjsRoot/tgrl1_logGumTeethAngle/tgrl1_logGumTeethMove/tgrl1_tongue.blendShape.tongue_down": 0,
            "tgrl1_dmyHeadObjsRoot/tgrl1_logGumTeethAngle/tgrl1_logGumTeethMove/tgrl1_tongue.blendShape.tongue_F007": 0,
            "tgrl1_dmyHeadObjsRoot/tgrl1_logGumTeethAngle/tgrl1_logGumTeethMove/tgrl1_tongue.blendShape.tongue_F007left": 0,
            "tgrl1_dmyHeadObjsRoot/tgrl1_logGumTeethAngle/tgrl1_logGumTeethMove/tgrl1_tongue.blendShape.tongue_left": 0,
            "tgrl1_dmyHeadObjsRoot/tgrl1_logGumTeethAngle/tgrl1_logGumTeethMove/tgrl1_tongue.blendShape.tongue_O": 0,
            "tgrl1_dmyHeadObjsRoot/tgrl1_logGumTeethAngle/tgrl1_logGumTeethMove/tgrl1_tongue.blendShape.tongue_out": 0,
            "tgrl1_dmyHeadObjsRoot/tgrl1_logGumTeethAngle/tgrl1_logGumTeethMove/tgrl1_tongue.blendShape.tongue_right": 0,
            "tgrl1_dmyHeadObjsRoot/tgrl1_logGumTeethAngle/tgrl1_logGumTeethMove/tgrl1_tongue.blendShape.tongue_up": 0,
            "rig_CharRoot/bip/bip Pelvis/bip Spine/bip Spine1/bip Neck/bip Head/rig_boneTongue.m_LocalPosition.x": -0.0188717656,
            "rig_CharRoot/bip/bip Pelvis/bip Spine/bip Spine1/bip Neck/bip Head/rig_boneTongue.m_LocalPosition.y": 0.0733392909,
            "rig_CharRoot/bip/bip Pelvis/bip Spine/bip Spine1/bip Neck/bip Head/rig_boneTongue.m_LocalPosition.z": 1.52587887E-07,
            "rig_CharRoot/bip/bip Pelvis/bip Spine/bip Spine1/bip Neck/bip Head/rig_boneTongue.localEulerAnglesRaw.x": 178.884003,
            "rig_CharRoot/bip/bip Pelvis/bip Spine/bip Spine1/bip Neck/bip Head/rig_boneTongue.localEulerAnglesRaw.y": 89.9999924,
            "rig_CharRoot/bip/bip Pelvis/bip Spine/bip Spine1/bip Neck/bip Head/rig_boneTongue.localEulerAnglesRaw.z": 0,
            "rig_CharRoot/bip/bip Pelvis/bip Spine/bip Spine1/bip Neck/bip Head/rig_boneTongue.m_LocalScale.x": 1,
            "rig_CharRoot/bip/bip Pelvis/bip Spine/bip Spine1/bip Neck/bip Head/rig_boneTongue.m_LocalScale.y": 1,
            "rig_CharRoot/bip/bip Pelvis/bip Spine/bip Spine1/bip Neck/bip Head/rig_boneTongue.m_LocalScale.z": 1,
            "muscle15": 0,
            "muscle17": 0
          },
          "strings": {},
          "inTangent": 0,
          "inWeight": 0.333333343,
          "outTangent": 0,
          "outWeight": 0.333333343,
          "weightedMode": 0
        }
      ]
    },
    {
      "properties": [
        "Face Animation Neutra"
      ],
      "loops": false,
      "keyFrames": [
        {
          "property": "Face Animation Neutra",
          "index": 0,
          "time": 0,
          "ints": {},
          "floats": {
            "girl_head_.blendShape.mClose": 100,
            "girl_head_.blendShape.A": 0,
            "girl_head_.blendShape.Cons": 0,
            "girl_head_.blendShape.Fv": 0,
            "girl_head_.blendShape.mLSide": 0,
            "girl_head_.blendShape.mLSideUp": 0,
            "girl_head_.blendShape.mRSide": 0,
            "girl_head_.blendShape.mRSideUp": 0,
            "girl_head_.blendShape.O": 0,
            "girl_head_.blendShape.smile": 0,
            "girl_head_.blendShape.U": 0,
            "girl_hair.blendShape.cheek1": 0,
            "girl_hair.blendShape.cheek2": 0,
            "girl_hair.blendShape.cheek3": 0,
            "girl_head_.blendShape.Bmp": 0,
            "girl_head_.blendShape.E": 0,
            "girl_head_.blendShape.F001": 0,
            "girl_head_.blendShape.F003": 0,
            "girl_head_.blendShape.F005": 0,
            "girl_head_.blendShape.F006": 0,
            "girl_head_.blendShape.F007": 0,
            "girl_head_.blendShape.F007left": 0,
            "girl_head_.blendShape.F008": 0,
            "girl_head_.blendShape.F017": 0,
            "girl_head_.blendShape.F019": 0,
            "girl_head_.blendShape.F024": 0,
            "girl_head_.blendShape.F031": 0,
            "girl_head_.blendShape.LEyeBMad": 0,
            "girl_head_.blendShape.LEyeClose": 0,
            "girl_head_.blendShape.LEyeLidUp": 0,
            "girl_head_.blendShape.LEyeMad": 0,
            "girl_head_.blendShape.LEyeSad": 0,
            "girl_head_.blendShape.LeyeBUp": 0,
            "girl_head_.blendShape.mSad": 0,
            "girl_head_.blendShape.REyeBMad": 0,
            "girl_head_.blendShape.REyeClose": 0,
            "girl_head_.blendShape.REyeLidUp": 0,
            "girl_head_.blendShape.REyeMad": 0,
            "girl_head_.blendShape.REyeSad": 0,
            "girl_head_.blendShape.ReyeBSad": 0,
            "girl_head_.blendShape.ReyeBUp": 0,
            "girl_head_.blendShape.ReyeLSad": 0,
            "tgrl1_dmyHeadObjsRoot/tgrl1_logGumTeethAngle/tgrl1_logGumTeethMove/tgrl1_tongue.blendShape.tongue_A": 0,
            "tgrl1_dmyHeadObjsRoot/tgrl1_logGumTeethAngle/tgrl1_logGumTeethMove/tgrl1_tongue.blendShape.tongue_down": 0,
            "tgrl1_dmyHeadObjsRoot/tgrl1_logGumTeethAngle/tgrl1_logGumTeethMove/tgrl1_tongue.blendShape.tongue_F007": 0,
            "tgrl1_dmyHeadObjsRoot/tgrl1_logGumTeethAngle/tgrl1_logGumTeethMove/tgrl1_tongue.blendShape.tongue_F007left": 0,
            "tgrl1_dmyHeadObjsRoot/tgrl1_logGumTeethAngle/tgrl1_logGumTeethMove/tgrl1_tongue.blendShape.tongue_left": 0,
            "tgrl1_dmyHeadObjsRoot/tgrl1_logGumTeethAngle/tgrl1_logGumTeethMove/tgrl1_tongue.blendShape.tongue_O": 0,
            "tgrl1_dmyHeadObjsRoot/tgrl1_logGumTeethAngle/tgrl1_logGumTeethMove/tgrl1_tongue.blendShape.tongue_out": 0,
            "tgrl1_dmyHeadObjsRoot/tgrl1_logGumTeethAngle/tgrl1_logGumTeethMove/tgrl1_tongue.blendShape.tongue_right": 0,
            "tgrl1_dmyHeadObjsRoot/tgrl1_logGumTeethAngle/tgrl1_logGumTeethMove/tgrl1_tongue.blendShape.tongue_up": 0,
            "rig_CharRoot/bip/bip Pelvis/bip Spine/bip Spine1/bip Neck/bip Head/rig_boneTongue.m_LocalPosition.x": -0.0188717656,
            "rig_CharRoot/bip/bip Pelvis/bip Spine/bip Spine1/bip Neck/bip Head/rig_boneTongue.m_LocalPosition.y": 0.0733392909,
            "rig_CharRoot/bip/bip Pelvis/bip Spine/bip Spine1/bip Neck/bip Head/rig_boneTongue.m_LocalPosition.z": 1.52587887E-07,
            "rig_CharRoot/bip/bip Pelvis/bip Spine/bip Spine1/bip Neck/bip Head/rig_boneTongue.localEulerAnglesRaw.x": 178.884003,
            "rig_CharRoot/bip/bip Pelvis/bip Spine/bip Spine1/bip Neck/bip Head/rig_boneTongue.localEulerAnglesRaw.y": 89.9999924,
            "rig_CharRoot/bip/bip Pelvis/bip Spine/bip Spine1/bip Neck/bip Head/rig_boneTongue.localEulerAnglesRaw.z": 0,
            "rig_CharRoot/bip/bip Pelvis/bip Spine/bip Spine1/bip Neck/bip Head/rig_boneTongue.m_LocalScale.x": 1,
            "rig_CharRoot/bip/bip Pelvis/bip Spine/bip Spine1/bip Neck/bip Head/rig_boneTongue.m_LocalScale.y": 1,
            "rig_CharRoot/bip/bip Pelvis/bip Spine/bip Spine1/bip Neck/bip Head/rig_boneTongue.m_LocalScale.z": 1,
            "muscle15": 0,
            "muscle17": 0
          },
          "strings": {},
          "inTangent": 0,
          "inWeight": 0.333333343,
          "outTangent": 0,
          "outWeight": 0.333333343,
          "weightedMode": 0
        }
      ]
    }
  ],
  "linguisticTags": {},
  "version": 12,
  "globalSpeed": 1.42142868,
  "globalRepetitions": 1
}
