{
  "linguisticTags": {
    "expression": "",
    "adverb": "",
    "noun": "",
    "pronoun": "",
    "verb": ""
  },
  "version": "17",
  "globalSpeed": "1",
  "globalRepetitions": "1",
  "facialExpressions": [
    [
      "1.010101",
      "Neutra"
    ],
    [
      "1.267676",
      "Neutra"
    ],
    [
      "1.520201",
      "Neutra"
    ],
    [
      "1.767676",
      "Neutra"
    ],
    [
      "2.0101",
      "Neutra"
    ],
    [
      "2.267676",
      "Neutra"
    ],
    [
      "2.772726",
      "Neutra"
    ]
  ],
  "leftHandPoses": [
    [
      "1.010101",
      "palma"
    ],
    [
      "1.267676",
      "palma"
    ],
    [
      "1.520201",
      "palma"
    ],
    [
      "1.767676",
      "palma"
    ],
    [
      "2.0101",
      "palma"
    ],
    [
      "2.267676",
      "palma"
    ],
    [
      "2.772726",
      "palma"
    ]
  ],
  "rightHandPoses": [
    [
      "1.010101",
      "E_aberto"
    ],
    [
      "1.267676",
      "E_aberto"
    ],
    [
      "1.520201",
      "E_aberto"
    ],
    [
      "1.767676",
      "E_aberto"
    ],
    [
      "2.0101",
      "E_aberto"
    ],
    [
      "2.267676",
      "E_aberto"
    ],
    [
      "2.772726",
      "E_aberto"
    ]
  ],
  "leftHandPositions": [
    {
      "time": "1.010101",
      "x": "-0.2132077",
      "y": "0",
      "z": "0"
    },
    {
      "time": "1.267676",
      "x": "-0.2132077",
      "y": "0",
      "z": "0"
    },
    {
      "time": "1.520201",
      "x": "-0.2132077",
      "y": "0",
      "z": "0"
    },
    {
      "time": "1.767676",
      "x": "-0.2132077",
      "y": "0",
      "z": "0"
    },
    {
      "time": "2.0101",
      "x": "-0.2132077",
      "y": "0",
      "z": "0"
    },
    {
      "time": "2.267676",
      "x": "-0.2132077",
      "y": "0",
      "z": "0"
    },
    {
      "time": "2.772726",
      "x": "-0.08749199",
      "y": "-0.1570788",
      "z": "0.2047963"
    }
  ],
  "rightHandPositions": [
    {
      "time": "1.010101",
      "x": "-0.2132077",
      "y": "0",
      "z": "0"
    },
    {
      "time": "1.267676",
      "x": "-0.2132077",
      "y": "0",
      "z": "0"
    },
    {
      "time": "1.520201",
      "x": "-0.2132077",
      "y": "0",
      "z": "0"
    },
    {
      "time": "1.767676",
      "x": "-0.2132077",
      "y": "0",
      "z": "0"
    },
    {
      "time": "2.0101",
      "x": "-0.2132077",
      "y": "0",
      "z": "0"
    },
    {
      "time": "2.267676",
      "x": "-0.2132077",
      "y": "0",
      "z": "0"
    },
    {
      "time": "2.772726",
      "x": "0.1761799",
      "y": "-0.1883288",
      "z": "0.2438588"
    }
  ]
}
