{
  "linguisticTags": {
    "expression": "",
    "adverb": "",
    "noun": "",
    "pronoun": "",
    "verb": ""
  },
  "version": "17",
  "globalSpeed": "1",
  "globalRepetitions": "1",
  "facialExpressions": [
    [
      "2",
      "Neutra"
    ],
    [
      "3",
      "Neutra"
    ]
  ],
  "leftHandPoses": [
    [
      "2",
      "C"
    ],
    [
      "3",
      "C"
    ]
  ],
  "rightHandPoses": [
    [
      "2",
      "C"
    ],
    [
      "3",
      "C"
    ]
  ],
  "leftHandPositions": [
    {
      "time": "2",
      "x": "-0.2132077",
      "y": "0",
      "z": "0"
    },
    {
      "time": "3",
      "x": "-0.1011639",
      "y": "-0.1814929",
      "z": "0.2345815"
    }
  ],
  "rightHandPositions": [
    {
      "time": "2",
      "x": "-0.2132077",
      "y": "0",
      "z": "0"
    },
    {
      "time": "3",
      "x": "0.1273518",
      "y": "-0.1814929",
      "z": "0.2375112"
    }
  ]
}
